[{"id":null,"href":"http://www.huffpostarabi.com/?country=AR","name":null,"onclick":null,"text":"","style":null,"title":null,"className":"dropdown__column__row","yPosition":100,"xPosition":99,"width":199,"height":39},{"id":null,"href":"http://www.huffingtonpost.com.au/?country=AU","name":null,"onclick":null,"text":"","style":null,"title":null,"className":"dropdown__column__row","yPosition":139,"xPosition":99,"width":199,"height":39},{"id":null,"href":"http://www.brasilpost.com.br/?country=BR","name":null,"onclick":null,"text":"","style":null,"title":null,"className":"dropdown__column__row","yPosition":178,"xPosition":99,"width":199,"height":39},{"id":null,"href":"http://www.huffingtonpost.ca/?country=CA","name":null,"onclick":null,"text":"","style":null,"title":null,"className":"dropdown__column__row","yPosition":217,"xPosition":99,"width":199,"height":39},{"id":null,"href":"http://www.huffingtonpost.de/?country=DE","name":null,"onclick":null,"text":"","style":null,"title":null,"className":"dropdown__column__row","yPosition":256,"xPosition":99,"width":199,"height":39},{"id":null,"href":"http://www.huffingtonpost.es/?country=ES","name":null,"onclick":null,"text":"","style":null,"title":null,"className":"dropdown__column__row","yPosition":295,"xPosition":99,"width":199,"height":39},{"id":null,"href":"http://www.huffingtonpost.fr/?country=FR","name":null,"onclick":null,"text":"","style":null,"title":null,"className":"dropdown__column__row","yPosition":334,"xPosition":99,"width":199,"height":39},{"id":null,"href":"http://www.huffingtonpost.gr/?country=GR","name":null,"onclick":null,"text":"","style":null,"title":null,"className":"dropdown__column__row","yPosition":373,"xPosition":99,"width":199,"height":39},{"id":null,"href":"http://www.huffingtonpost.in/?country=IN","name":null,"onclick":null,"text":"","style":null,"title":null,"className":"dropdown__column__row","yPosition":100,"xPosition":299,"width":199,"height":39},{"id":null,"href":"http://www.huffingtonpost.it/?country=IT","name":null,"onclick":null,"text":"","style":null,"title":null,"className":"dropdown__column__row","yPosition":139,"xPosition":299,"width":199,"height":39},{"id":null,"href":"http://www.huffingtonpost.jp/?country=JP","name":null,"onclick":null,"text":"","style":null,"title":null,"className":"dropdown__column__row","yPosition":178,"xPosition":299,"width":199,"height":39},{"id":null,"href":"http://www.huffingtonpost.kr/?country=KR","name":null,"onclick":null,"text":"","style":null,"title":null,"className":"dropdown__column__row","yPosition":217,"xPosition":299,"width":199,"height":39},{"id":null,"href":"http://www.huffpostmaghreb.com/?country=MG","name":null,"onclick":null,"text":"","style":null,"title":null,"className":"dropdown__column__row","yPosition":256,"xPosition":299,"width":199,"height":39},{"id":null,"href":"http://www.huffingtonpost.com.mx/?country=MX","name":null,"onclick":null,"text":"","style":null,"title":null,"className":"dropdown__column__row","yPosition":295,"xPosition":299,"width":199,"height":39},{"id":null,"href":"http://www.huffingtonpost.co.uk/?country=UK","name":null,"onclick":null,"text":"","style":null,"title":null,"className":"dropdown__column__row","yPosition":334,"xPosition":299,"width":199,"height":39},{"id":null,"href":"http://www.huffingtonpost.com/?country=US","name":null,"onclick":null,"text":"","style":null,"title":null,"className":"dropdown__column__row","yPosition":373,"xPosition":299,"width":199,"height":39},{"id":null,"href":"/","name":null,"onclick":null,"text":"","style":null,"title":null,"className":"logo","yPosition":16,"xPosition":478,"width":410,"height":30},{"id":null,"href":"https://twitter.com/HuffingtonPost","name":null,"onclick":null,"text":"","style":null,"title":null,"className":"social-list__item social-list__item--twitter","yPosition":13,"xPosition":1109,"width":45,"height":54},{"id":null,"href":"http://facebook.com/HuffingtonPost","name":null,"onclick":null,"text":"","style":null,"title":null,"className":"social-list__item social-list__item--facebook","yPosition":13,"xPosition":1155,"width":45,"height":54},{"id":null,"href":"http://pinterest.com/huffingtonpost","name":null,"onclick":null,"text":"","style":null,"title":null,"className":"social-list__item social-list__item--pinterest","yPosition":13,"xPosition":1201,"width":45,"height":54},{"id":null,"href":"http://www.huffingtonpost.com/","name":null,"onclick":null,"text":"NEWS","style":null,"title":null,"className":"nav__item__link","yPosition":96,"xPosition":126,"width":42,"height":17},{"id":null,"href":"http://www.huffingtonpost.com/section/world","name":null,"onclick":null,"text":"","style":null,"title":null,"className":"dropdown__column__row--link","yPosition":149,"xPosition":99,"width":198,"height":39},{"id":null,"href":"http://highline.huffingtonpost.com/","name":null,"onclick":null,"text":"","style":null,"title":null,"className":"dropdown__column__row--link","yPosition":188,"xPosition":99,"width":198,"height":39},{"id":null,"href":"http://www.huffingtonpost.com/science/","name":null,"onclick":null,"text":"","style":null,"title":null,"className":"dropdown__column__row--link","yPosition":227,"xPosition":99,"width":198,"height":39},{"id":null,"href":"http://www.huffingtonpost.com/section/education","name":null,"onclick":null,"text":"","style":null,"title":null,"className":"dropdown__column__row--link","yPosition":266,"xPosition":99,"width":198,"height":39},{"id":null,"href":"http://www.huffingtonpost.com/section/weird-news","name":null,"onclick":null,"text":"","style":null,"title":null,"className":"dropdown__column__row--link","yPosition":305,"xPosition":99,"width":198,"height":39},{"id":null,"href":"http://www.huffingtonpost.com/section/business","name":null,"onclick":null,"text":"","style":null,"title":null,"className":"dropdown__column__row--link","yPosition":149,"xPosition":298,"width":198,"height":39},{"id":null,"href":"http://testkitchen.huffingtonpost.com/","name":null,"onclick":null,"text":"","style":null,"title":null,"className":"dropdown__column__row--link","yPosition":188,"xPosition":298,"width":198,"height":39},{"id":null,"href":"http://www.huffingtonpost.com/section/technology","name":null,"onclick":null,"text":"","style":null,"title":null,"className":"dropdown__column__row--link","yPosition":227,"xPosition":298,"width":198,"height":39},{"id":null,"href":"http://www.huffingtonpost.com/section/college","name":null,"onclick":null,"text":"","style":null,"title":null,"className":"dropdown__column__row--link","yPosition":266,"xPosition":298,"width":198,"height":39},{"id":null,"href":"http://www.huffingtonpost.com/media/","name":null,"onclick":null,"text":"","style":null,"title":null,"className":"dropdown__column__row--link","yPosition":305,"xPosition":298,"width":198,"height":39},{"id":null,"href":"http://www.huffingtonpost.com/entry/donald-trump-strongmen_us_57e7faabe4b08d73b831df76?","name":null,"onclick":null,"text":"","style":null,"title":null,"className":"dropdown__column__row dropdown__column__row--entry dropdown__column__row--link","yPosition":129,"xPosition":497,"width":256,"height":112},{"id":null,"href":"http://www.huffingtonpost.com/entry/donald-trump-strongmen_us_57e7faabe4b08d73b831df76?","name":null,"onclick":null,"text":"","style":null,"title":null,"className":"dropdown__column__row dropdown__column__row--entry dropdown__column__row--link","yPosition":129,"xPosition":754,"width":256,"height":132},{"id":null,"href":"http://www.huffingtonpost.com/entry/donald-trump-campaign-manager-debate_us_57e917a7e4b08d73b8322381?section=&","name":null,"onclick":null,"text":"","style":null,"title":null,"className":"dropdown__column__row dropdown__column__row--entry dropdown__column__row--link","yPosition":261,"xPosition":754,"width":256,"height":132},{"id":null,"href":"http://www.huffingtonpost.com/entry/donald-trump-stop-and-frisk_us_57e58d02e4b0e80b1ba21291?section=&","name":null,"onclick":null,"text":"","style":null,"title":null,"className":"dropdown__column__row dropdown__column__row--entry dropdown__column__row--link","yPosition":129,"xPosition":1012,"width":255,"height":132},{"id":null,"href":"http://www.bloomberg.com/news/articles/2016-09-26/disney-working-with-adviser-on-potential-twitter-bid","name":null,"onclick":null,"text":"","style":null,"title":null,"className":"dropdown__column__row dropdown__column__row--entry dropdown__column__row--link","yPosition":261,"xPosition":1012,"width":255,"height":132},{"id":null,"href":"http://www.huffingtonpost.com/section/politics","name":null,"onclick":null,"text":"POLITICS","style":null,"title":null,"className":"nav__item__link","yPosition":96,"xPosition":225,"width":66,"height":17},{"id":null,"href":"http://elections.huffingtonpost.com/pollster","name":null,"onclick":null,"text":"","style":null,"title":null,"className":"dropdown__column__row--link","yPosition":149,"xPosition":99,"width":198,"height":39},{"id":null,"href":"http://elections.huffingtonpost.com/","name":null,"onclick":null,"text":"","style":null,"title":null,"className":"dropdown__column__row--link","yPosition":188,"xPosition":99,"width":198,"height":39},{"id":null,"href":"http://www.huffingtonpost.com/news/eat-the-press/","name":null,"onclick":null,"text":"","style":null,"title":null,"className":"dropdown__column__row--link","yPosition":227,"xPosition":99,"width":198,"height":39},{"id":null,"href":"http://www.huffingtonpost.com/news/huffpost-hill/","name":null,"onclick":null,"text":"","style":null,"title":null,"className":"dropdown__column__row--link","yPosition":149,"xPosition":298,"width":198,"height":39},{"id":null,"href":"http://www.huffingtonpost.com/news/candidate-confessional-podcast/","name":null,"onclick":null,"text":"","style":null,"title":null,"className":"dropdown__column__row--link","yPosition":188,"xPosition":298,"width":198,"height":58},{"id":null,"href":"http://www.huffingtonpost.com/news/so-that-happened/","name":null,"onclick":null,"text":"","style":null,"title":null,"className":"dropdown__column__row--link","yPosition":246,"xPosition":298,"width":198,"height":39},{"id":null,"href":"http://www.huffingtonpost.com/entry/first-presidential-debate-trump-clinton_us_57e53a55e4b0e28b2b536a08?","name":null,"onclick":null,"text":"","style":null,"title":null,"className":"dropdown__column__row dropdown__column__row--entry dropdown__column__row--link","yPosition":129,"xPosition":497,"width":256,"height":136},{"id":null,"href":"http://www.huffingtonpost.com/entry/trump-luxury-jet_us_57e6bc0ee4b08d73b8319f15?section=&section=us_politics","name":null,"onclick":null,"text":"","style":null,"title":null,"className":"dropdown__column__row dropdown__column__row--entry dropdown__column__row--link","yPosition":129,"xPosition":754,"width":256,"height":132},{"id":null,"href":"http://www.huffingtonpost.com/entry/expectations-schmexpectations_us_57e53dcbe4b0e80b1ba18299?section=&section=us_politics","name":null,"onclick":null,"text":"","style":null,"title":null,"className":"dropdown__column__row dropdown__column__row--entry dropdown__column__row--link","yPosition":261,"xPosition":754,"width":256,"height":132},{"id":null,"href":"http://www.huffingtonpost.com/entry/still-not-enough-treatment-in-heart-of-the-opioid-crisis_us_57e92a9de4b00267764fc8a9?section=&section=us_politics","name":null,"onclick":null,"text":"","style":null,"title":null,"className":"dropdown__column__row dropdown__column__row--entry dropdown__column__row--link","yPosition":129,"xPosition":1012,"width":255,"height":132},{"id":null,"href":"http://www.huffingtonpost.com/entry/charlotte-activists-release-demands_us_57e5876ae4b08d73b8314cdc?section=&section=us_politics","name":null,"onclick":null,"text":"","style":null,"title":null,"className":"dropdown__column__row dropdown__column__row--entry dropdown__column__row--link","yPosition":261,"xPosition":1012,"width":255,"height":132},{"id":null,"href":"http://www.huffingtonpost.com/dept/entertainment","name":null,"onclick":null,"text":"ENTERTAINMENT","style":null,"title":null,"className":"nav__item__link","yPosition":96,"xPosition":349,"width":121,"height":17},{"id":null,"href":"http://www.huffingtonpost.com/section/sports","name":null,"onclick":null,"text":"","style":null,"title":null,"className":"dropdown__column__row--link","yPosition":149,"xPosition":99,"width":198,"height":39},{"id":null,"href":"http://www.huffingtonpost.com/section/comedy","name":null,"onclick":null,"text":"","style":null,"title":null,"className":"dropdown__column__row--link","yPosition":188,"xPosition":99,"width":198,"height":39},{"id":null,"href":"http://www.huffingtonpost.com/section/celebrity","name":null,"onclick":null,"text":"","style":null,"title":null,"className":"dropdown__column__row--link","yPosition":227,"xPosition":99,"width":198,"height":39},{"id":null,"href":"http://www.huffingtonpost.com/section/books","name":null,"onclick":null,"text":"","style":null,"title":null,"className":"dropdown__column__row--link","yPosition":266,"xPosition":99,"width":198,"height":39},{"id":null,"href":"http://www.huffingtonpost.com/section/entertainment","name":null,"onclick":null,"text":"","style":null,"title":null,"className":"dropdown__column__row--link","yPosition":149,"xPosition":298,"width":198,"height":39},{"id":null,"href":"http://www.huffingtonpost.com/section/tv","name":null,"onclick":null,"text":"","style":null,"title":null,"className":"dropdown__column__row--link","yPosition":188,"xPosition":298,"width":198,"height":39},{"id":null,"href":"http://www.huffingtonpost.com/section/arts","name":null,"onclick":null,"text":"","style":null,"title":null,"className":"dropdown__column__row--link","yPosition":227,"xPosition":298,"width":198,"height":39},{"id":null,"href":"http://www.huffingtonpost.com/entry/amy-schumer-and-her-boyfriend-hit-a-home-run-with-hilarious-kiss-cam-appearance_us_57e9118ee4b0e28b2b54cffe?","name":null,"onclick":null,"text":"","style":null,"title":null,"className":"dropdown__column__row dropdown__column__row--entry dropdown__column__row--link","yPosition":129,"xPosition":497,"width":256,"height":136},{"id":null,"href":"http://www.huffingtonpost.com/entry/jada-pinkett-smith-shares-touching-birthday-message-to-husband-will-on-facebook_us_57e951c1e4b0e28b2b552c1c?section=&","name":null,"onclick":null,"text":"","style":null,"title":null,"className":"dropdown__column__row dropdown__column__row--entry dropdown__column__row--link","yPosition":129,"xPosition":754,"width":256,"height":132},{"id":null,"href":"http://www.huffingtonpost.com/entry/zach-galifianakis-donald-trump-between-two-ferns_us_57e956e6e4b0e28b2b553767?section=&","name":null,"onclick":null,"text":"","style":null,"title":null,"className":"dropdown__column__row dropdown__column__row--entry dropdown__column__row--link","yPosition":261,"xPosition":754,"width":256,"height":132},{"id":null,"href":"http://www.huffingtonpost.com/entry/john-travolta-opens-up-about-son-jetts-tragic-death-in-2009_us_57e95212e4b08d73b8327e42?section=&","name":null,"onclick":null,"text":"","style":null,"title":null,"className":"dropdown__column__row dropdown__column__row--entry dropdown__column__row--link","yPosition":129,"xPosition":1012,"width":255,"height":132},{"id":null,"href":"http://www.huffingtonpost.com/entry/ronan-farrow-remembers-late-brother-thaddeus-with-sweet-photos_us_57e56e99e4b0e28b2b53ccf8?section=&","name":null,"onclick":null,"text":"","style":null,"title":null,"className":"dropdown__column__row dropdown__column__row--entry dropdown__column__row--link","yPosition":261,"xPosition":1012,"width":255,"height":132},{"id":null,"href":"http://www.huffingtonpost.com/dept/wellness","name":null,"onclick":null,"text":"WELLNESS","style":null,"title":null,"className":"nav__item__link","yPosition":96,"xPosition":527,"width":76,"height":17},{"id":null,"href":"http://www.huffingtonpost.com/section/healthy-living","name":null,"onclick":null,"text":"","style":null,"title":null,"className":"dropdown__column__row--link","yPosition":149,"xPosition":99,"width":198,"height":39},{"id":null,"href":"http://www.huffingtonpost.com/section/travel","name":null,"onclick":null,"text":"","style":null,"title":null,"className":"dropdown__column__row--link","yPosition":188,"xPosition":99,"width":198,"height":39},{"id":null,"href":"http://www.huffingtonpost.com/section/style","name":null,"onclick":null,"text":"","style":null,"title":null,"className":"dropdown__column__row--link","yPosition":227,"xPosition":99,"width":198,"height":39},{"id":null,"href":"http://www.huffingtonpost.com/section/taste","name":null,"onclick":null,"text":"","style":null,"title":null,"className":"dropdown__column__row--link","yPosition":266,"xPosition":99,"width":198,"height":39},{"id":null,"href":"http://www.huffingtonpost.com/section/huffpost-home","name":null,"onclick":null,"text":"","style":null,"title":null,"className":"dropdown__column__row--link","yPosition":305,"xPosition":99,"width":198,"height":39},{"id":null,"href":"http://www.huffingtonpost.com/section/weddings","name":null,"onclick":null,"text":"","style":null,"title":null,"className":"dropdown__column__row--link","yPosition":149,"xPosition":298,"width":198,"height":39},{"id":null,"href":"http://www.huffingtonpost.com/section/divorce","name":null,"onclick":null,"text":"","style":null,"title":null,"className":"dropdown__column__row--link","yPosition":188,"xPosition":298,"width":198,"height":39},{"id":null,"href":"http://www.huffingtonpost.com/news/sleep--wellness/","name":null,"onclick":null,"text":"","style":null,"title":null,"className":"dropdown__column__row--link","yPosition":227,"xPosition":298,"width":198,"height":39},{"id":null,"href":"http://www.huffingtonpost.com/section/gps-for-the-soul","name":null,"onclick":null,"text":"","style":null,"title":null,"className":"dropdown__column__row--link","yPosition":266,"xPosition":298,"width":198,"height":39},{"id":null,"href":"http://www.huffingtonpost.com/entry/soups-for-health_us_57e3e915e4b0e80b1ba091ea?","name":null,"onclick":null,"text":"","style":null,"title":null,"className":"dropdown__column__row dropdown__column__row--entry dropdown__column__row--link","yPosition":129,"xPosition":497,"width":256,"height":112},{"id":null,"href":"http://www.huffingtonpost.com/entry/prince-george-high-five-justin-trudeau_us_57e91b33e4b0e28b2b54d6f9?","name":null,"onclick":null,"text":"","style":null,"title":null,"className":"dropdown__column__row dropdown__column__row--entry dropdown__column__row--link","yPosition":129,"xPosition":754,"width":256,"height":132},{"id":null,"href":"http://www.huffingtonpost.com/entry/arnold-palmer-iced-tea-lemonade-drink_us_57e8b4fae4b08d73b8321068?","name":null,"onclick":null,"text":"","style":null,"title":null,"className":"dropdown__column__row dropdown__column__row--entry dropdown__column__row--link","yPosition":261,"xPosition":754,"width":256,"height":132},{"id":null,"href":"http://www.huffingtonpost.com/entry/crohns-disease-cause_us_57e40374e4b0e28b2b52a67c?","name":null,"onclick":null,"text":"","style":null,"title":null,"className":"dropdown__column__row dropdown__column__row--entry dropdown__column__row--link","yPosition":129,"xPosition":1012,"width":255,"height":132},{"id":null,"href":"http://www.huffingtonpost.com/entry/barack-obama-anthony-bourdain-hot-dogs_us_57e89415e4b08d73b83208d5?","name":null,"onclick":null,"text":"","style":null,"title":null,"className":"dropdown__column__row dropdown__column__row--entry dropdown__column__row--link","yPosition":261,"xPosition":1012,"width":255,"height":132},{"id":null,"href":"http://www.huffingtonpost.com/dept/whats-working","name":null,"onclick":null,"text":"WHAT’S WORKING","style":null,"title":null,"className":"nav__item__link","yPosition":96,"xPosition":660,"width":130,"height":17},{"id":null,"href":"http://www.huffingtonpost.com/impact/","name":null,"onclick":null,"text":"","style":null,"title":null,"className":"dropdown__column__row--link","yPosition":149,"xPosition":99,"width":198,"height":39},{"id":null,"href":"http://www.huffingtonpost.com/green/","name":null,"onclick":null,"text":"","style":null,"title":null,"className":"dropdown__column__row--link","yPosition":188,"xPosition":99,"width":198,"height":39},{"id":null,"href":"http://www.huffingtonpost.com/section/good-news","name":null,"onclick":null,"text":"","style":null,"title":null,"className":"dropdown__column__row--link","yPosition":149,"xPosition":298,"width":198,"height":39},{"id":null,"href":"http://www.huffingtonpost.com/news/global-health/","name":null,"onclick":null,"text":"","style":null,"title":null,"className":"dropdown__column__row--link","yPosition":188,"xPosition":298,"width":198,"height":39},{"id":null,"href":"http://www.huffingtonpost.com/entry/getting-rid-of-80-percent-of-closet_us_57df3b31e4b04a1497b5188e?","name":null,"onclick":null,"text":"","style":null,"title":null,"className":"dropdown__column__row dropdown__column__row--entry dropdown__column__row--link","yPosition":129,"xPosition":497,"width":256,"height":136},{"id":null,"href":"http://www.huffingtonpost.com/entry/these-inmates-did-a-facebook-live-from-the-county-jail_us_57e73af2e4b09f67131e4650?","name":null,"onclick":null,"text":"","style":null,"title":null,"className":"dropdown__column__row dropdown__column__row--entry dropdown__column__row--link","yPosition":129,"xPosition":754,"width":256,"height":132},{"id":null,"href":"http://www.huffingtonpost.com/entry/real-junk-food-project-supermarket-warehouse_us_57e424d5e4b0e80b1ba0e6a4?","name":null,"onclick":null,"text":"","style":null,"title":null,"className":"dropdown__column__row dropdown__column__row--entry dropdown__column__row--link","yPosition":261,"xPosition":754,"width":256,"height":132},{"id":null,"href":"http://www.huffingtonpost.com/entry/kellie-jones-macarthur-curator-black-art-history_us_57e527e2e4b0e80b1ba172b8?","name":null,"onclick":null,"text":"","style":null,"title":null,"className":"dropdown__column__row dropdown__column__row--entry dropdown__column__row--link","yPosition":129,"xPosition":1012,"width":255,"height":132},{"id":null,"href":"http://www.huffingtonpost.com/entry/what-your-favorite-piece-of-clothing-says-about-you_us_57e2c97ee4b0e80b1b9fc492?","name":null,"onclick":null,"text":"","style":null,"title":null,"className":"dropdown__column__row dropdown__column__row--entry dropdown__column__row--link","yPosition":261,"xPosition":1012,"width":255,"height":132},{"id":null,"href":"http://www.huffingtonpost.com/dept/voices","name":null,"onclick":null,"text":"VOICES","style":null,"title":null,"className":"nav__item__link","yPosition":96,"xPosition":847,"width":53,"height":17},{"id":null,"href":"http://www.huffingtonpost.com/section/black-voices","name":null,"onclick":null,"text":"","style":null,"title":null,"className":"dropdown__column__row--link","yPosition":149,"xPosition":99,"width":198,"height":39},{"id":null,"href":"http://www.huffingtonpost.com/section/latino-voices","name":null,"onclick":null,"text":"","style":null,"title":null,"className":"dropdown__column__row--link","yPosition":188,"xPosition":99,"width":198,"height":39},{"id":null,"href":"http://www.huffingtonpost.com/section/women","name":null,"onclick":null,"text":"","style":null,"title":null,"className":"dropdown__column__row--link","yPosition":227,"xPosition":99,"width":198,"height":39},{"id":null,"href":"http://www.huffingtonpost.com/section/fifty","name":null,"onclick":null,"text":"","style":null,"title":null,"className":"dropdown__column__row--link","yPosition":266,"xPosition":99,"width":198,"height":39},{"id":null,"href":"http://www.huffingtonpost.com/section/religion","name":null,"onclick":null,"text":"","style":null,"title":null,"className":"dropdown__column__row--link","yPosition":305,"xPosition":99,"width":198,"height":39},{"id":null,"href":"http://www.huffingtonpost.com/section/queer-voices","name":null,"onclick":null,"text":"","style":null,"title":null,"className":"dropdown__column__row--link","yPosition":149,"xPosition":298,"width":198,"height":39},{"id":null,"href":"http://www.huffingtonpost.com/section/parents","name":null,"onclick":null,"text":"","style":null,"title":null,"className":"dropdown__column__row--link","yPosition":188,"xPosition":298,"width":198,"height":39},{"id":null,"href":"http://www.huffingtonpost.com/section/teen","name":null,"onclick":null,"text":"","style":null,"title":null,"className":"dropdown__column__row--link","yPosition":227,"xPosition":298,"width":198,"height":39},{"id":null,"href":"http://www.huffingtonpost.com/section/college","name":null,"onclick":null,"text":"","style":null,"title":null,"className":"dropdown__column__row--link","yPosition":266,"xPosition":298,"width":198,"height":39},{"id":null,"href":"http://www.huffingtonpost.com/entry/community-gathers-to-mourn-13-year-old-tyre-king-who-was-shot-by-cops_us_57e90936e4b08d73b8321f36?","name":null,"onclick":null,"text":"","style":null,"title":null,"className":"dropdown__column__row dropdown__column__row--entry dropdown__column__row--link","yPosition":129,"xPosition":497,"width":256,"height":136},{"id":null,"href":"http://www.huffingtonpost.com/entry/hilaria-baldwin-postpartum-photo_us_57e92bb1e4b08d73b8323c92?","name":null,"onclick":null,"text":"","style":null,"title":null,"className":"dropdown__column__row dropdown__column__row--entry dropdown__column__row--link","yPosition":129,"xPosition":754,"width":256,"height":132},{"id":null,"href":"http://www.huffingtonpost.com/entry/emma-watson-made-a-stunning-short-film-about-the-hurdles-women-face_us_57e91f5ce4b0e80b1ba2e6db?","name":null,"onclick":null,"text":"","style":null,"title":null,"className":"dropdown__column__row dropdown__column__row--entry dropdown__column__row--link","yPosition":261,"xPosition":754,"width":256,"height":132},{"id":null,"href":"http://www.huffingtonpost.com/entry/us-police-killings-reminiscent-of-lynching-un-group-says_us_57e93538e4b08d73b8324c10?","name":null,"onclick":null,"text":"","style":null,"title":null,"className":"dropdown__column__row dropdown__column__row--entry dropdown__column__row--link","yPosition":129,"xPosition":1012,"width":255,"height":132},{"id":null,"href":"http://www.huffingtonpost.com/maritza-stanchich-phd/dark-star-puerto-rico-reels-from-3-day-blackout_b_12166262.html?","name":null,"onclick":null,"text":"","style":null,"title":null,"className":"dropdown__column__row dropdown__column__row--entry dropdown__column__row--link","yPosition":261,"xPosition":1012,"width":255,"height":132},{"id":null,"href":"http://www.huffingtonpost.com/section/video","name":null,"onclick":null,"text":"VIDEO","style":null,"title":null,"className":"nav__item__link","yPosition":96,"xPosition":957,"width":45,"height":17},{"id":null,"href":"http://www.huffingtonpost.com/section/arts","name":null,"onclick":null,"text":"","style":null,"title":null,"className":"dropdown__column__row--link","yPosition":149,"xPosition":99,"width":194,"height":39},{"id":null,"href":"http://www.huffingtonpost.com/section/black-voices","name":null,"onclick":null,"text":"","style":null,"title":null,"className":"dropdown__column__row--link","yPosition":188,"xPosition":99,"width":194,"height":39},{"id":null,"href":"http://www.huffingtonpost.com/section/books","name":null,"onclick":null,"text":"","style":null,"title":null,"className":"dropdown__column__row--link","yPosition":227,"xPosition":99,"width":194,"height":39},{"id":null,"href":"http://www.huffingtonpost.com/section/business","name":null,"onclick":null,"text":"","style":null,"title":null,"className":"dropdown__column__row--link","yPosition":266,"xPosition":99,"width":194,"height":39},{"id":null,"href":"http://www.huffingtonpost.com/news/candidate-confessional-podcast/","name":null,"onclick":null,"text":"","style":null,"title":null,"className":"dropdown__column__row--link","yPosition":305,"xPosition":99,"width":194,"height":58},{"id":null,"href":"http://www.huffingtonpost.com/section/celebrity","name":null,"onclick":null,"text":"","style":null,"title":null,"className":"dropdown__column__row--link","yPosition":363,"xPosition":99,"width":194,"height":39},{"id":null,"href":"http://www.huffingtonpost.com/section/college","name":null,"onclick":null,"text":"","style":null,"title":null,"className":"dropdown__column__row--link","yPosition":402,"xPosition":99,"width":194,"height":39},{"id":null,"href":"http://www.huffingtonpost.com/section/comedy","name":null,"onclick":null,"text":"","style":null,"title":null,"className":"dropdown__column__row--link","yPosition":441,"xPosition":99,"width":194,"height":39},{"id":null,"href":"http://www.huffingtonpost.com/section/crime","name":null,"onclick":null,"text":"","style":null,"title":null,"className":"dropdown__column__row--link","yPosition":480,"xPosition":99,"width":194,"height":39},{"id":null,"href":"http://www.huffingtonpost.com/section/divorce","name":null,"onclick":null,"text":"","style":null,"title":null,"className":"dropdown__column__row--link","yPosition":519,"xPosition":99,"width":194,"height":39},{"id":null,"href":"http://www.huffingtonpost.com/news/la-dolce-vita/","name":null,"onclick":null,"text":"","style":null,"title":null,"className":"dropdown__column__row--link","yPosition":558,"xPosition":99,"width":194,"height":39},{"id":null,"href":"http://www.huffingtonpost.com/news/eat-the-press/","name":null,"onclick":null,"text":"","style":null,"title":null,"className":"dropdown__column__row--link","yPosition":597,"xPosition":99,"width":194,"height":39},{"id":null,"href":"http://www.huffingtonpost.com/section/education","name":null,"onclick":null,"text":"","style":null,"title":null,"className":"dropdown__column__row--link","yPosition":149,"xPosition":294,"width":194,"height":39},{"id":null,"href":"http://elections.huffingtonpost.com/","name":null,"onclick":null,"text":"","style":null,"title":null,"className":"dropdown__column__row--link","yPosition":188,"xPosition":294,"width":194,"height":39},{"id":null,"href":"http://www.huffingtonpost.com/section/entertainment","name":null,"onclick":null,"text":"","style":null,"title":null,"className":"dropdown__column__row--link","yPosition":227,"xPosition":294,"width":194,"height":39},{"id":null,"href":"http://www.huffingtonpost.com/section/fifty","name":null,"onclick":null,"text":"","style":null,"title":null,"className":"dropdown__column__row--link","yPosition":266,"xPosition":294,"width":194,"height":39},{"id":null,"href":"http://www.huffingtonpost.com/section/good-news","name":null,"onclick":null,"text":"","style":null,"title":null,"className":"dropdown__column__row--link","yPosition":305,"xPosition":294,"width":194,"height":39},{"id":null,"href":"http://www.huffingtonpost.com/green/","name":null,"onclick":null,"text":"","style":null,"title":null,"className":"dropdown__column__row--link","yPosition":344,"xPosition":294,"width":194,"height":39},{"id":null,"href":"http://www.huffingtonpost.com/section/healthy-living","name":null,"onclick":null,"text":"","style":null,"title":null,"className":"dropdown__column__row--link","yPosition":383,"xPosition":294,"width":194,"height":39},{"id":null,"href":"http://highline.huffingtonpost.com/","name":null,"onclick":null,"text":"","style":null,"title":null,"className":"dropdown__column__row--link","yPosition":422,"xPosition":294,"width":194,"height":39},{"id":null,"href":"http://www.huffingtonpost.com/section/huffpost-home","name":null,"onclick":null,"text":"","style":null,"title":null,"className":"dropdown__column__row--link","yPosition":461,"xPosition":294,"width":194,"height":39},{"id":null,"href":"http://www.huffingtonpost.com/horoscopes/","name":null,"onclick":null,"text":"","style":null,"title":null,"className":"dropdown__column__row--link","yPosition":500,"xPosition":294,"width":194,"height":39},{"id":null,"href":"http://data.huffingtonpost.com/","name":null,"onclick":null,"text":"","style":null,"title":null,"className":"dropdown__column__row--link","yPosition":539,"xPosition":294,"width":194,"height":39},{"id":null,"href":"http://www.huffingtonpost.com/news/huffpost-hill/","name":null,"onclick":null,"text":"","style":null,"title":null,"className":"dropdown__column__row--link","yPosition":578,"xPosition":294,"width":194,"height":39},{"id":null,"href":"http://www.huffingtonpost.com/impact/","name":null,"onclick":null,"text":"","style":null,"title":null,"className":"dropdown__column__row--link","yPosition":149,"xPosition":489,"width":194,"height":39},{"id":null,"href":"http://www.huffingtonpost.com/section/latino-voices","name":null,"onclick":null,"text":"","style":null,"title":null,"className":"dropdown__column__row--link","yPosition":188,"xPosition":489,"width":194,"height":39},{"id":null,"href":"http://www.huffingtonpost.com/media/","name":null,"onclick":null,"text":"","style":null,"title":null,"className":"dropdown__column__row--link","yPosition":227,"xPosition":489,"width":194,"height":39},{"id":null,"href":"http://www.huffingtonpost.com/news/outspeak/","name":null,"onclick":null,"text":"","style":null,"title":null,"className":"dropdown__column__row--link","yPosition":266,"xPosition":489,"width":194,"height":39},{"id":null,"href":"http://www.huffingtonpost.com/section/parents","name":null,"onclick":null,"text":"","style":null,"title":null,"className":"dropdown__column__row--link","yPosition":305,"xPosition":489,"width":194,"height":39},{"id":null,"href":"http://www.huffingtonpost.com/section/politics","name":null,"onclick":null,"text":"","style":null,"title":null,"className":"dropdown__column__row--link","yPosition":344,"xPosition":489,"width":194,"height":39},{"id":null,"href":"http://elections.huffingtonpost.com/pollster","name":null,"onclick":null,"text":"","style":null,"title":null,"className":"dropdown__column__row--link","yPosition":383,"xPosition":489,"width":194,"height":39},{"id":null,"href":"http://www.huffingtonpost.com/section/queer-voices","name":null,"onclick":null,"text":"","style":null,"title":null,"className":"dropdown__column__row--link","yPosition":422,"xPosition":489,"width":194,"height":39},{"id":null,"href":"http://www.huffingtonpost.com/section/religion","name":null,"onclick":null,"text":"","style":null,"title":null,"className":"dropdown__column__row--link","yPosition":461,"xPosition":489,"width":194,"height":39},{"id":null,"href":"http://www.huffingtonpost.com/science/","name":null,"onclick":null,"text":"","style":null,"title":null,"className":"dropdown__column__row--link","yPosition":500,"xPosition":489,"width":194,"height":39},{"id":null,"href":"http://www.huffingtonpost.com/small-business/","name":null,"onclick":null,"text":"","style":null,"title":null,"className":"dropdown__column__row--link","yPosition":539,"xPosition":489,"width":194,"height":39},{"id":null,"href":"http://www.huffingtonpost.com/news/so-that-happened/","name":null,"onclick":null,"text":"","style":null,"title":null,"className":"dropdown__column__row--link","yPosition":578,"xPosition":489,"width":194,"height":39},{"id":null,"href":"http://www.huffingtonpost.com/section/sports","name":null,"onclick":null,"text":"","style":null,"title":null,"className":"dropdown__column__row--link","yPosition":149,"xPosition":684,"width":194,"height":39},{"id":null,"href":"http://www.huffingtonpost.com/section/style","name":null,"onclick":null,"text":"","style":null,"title":null,"className":"dropdown__column__row--link","yPosition":188,"xPosition":684,"width":194,"height":39},{"id":null,"href":"http://www.huffingtonpost.com/section/taste","name":null,"onclick":null,"text":"","style":null,"title":null,"className":"dropdown__column__row--link","yPosition":227,"xPosition":684,"width":194,"height":39},{"id":null,"href":"http://www.huffingtonpost.com/section/technology","name":null,"onclick":null,"text":"","style":null,"title":null,"className":"dropdown__column__row--link","yPosition":266,"xPosition":684,"width":194,"height":39},{"id":null,"href":"http://www.huffingtonpost.com/section/teen","name":null,"onclick":null,"text":"","style":null,"title":null,"className":"dropdown__column__row--link","yPosition":305,"xPosition":684,"width":194,"height":39},{"id":null,"href":"http://testkitchen.huffingtonpost.com/","name":null,"onclick":null,"text":"","style":null,"title":null,"className":"dropdown__column__row--link","yPosition":344,"xPosition":684,"width":194,"height":39},{"id":null,"href":"http://www.huffingtonpost.com/section/travel","name":null,"onclick":null,"text":"","style":null,"title":null,"className":"dropdown__column__row--link","yPosition":383,"xPosition":684,"width":194,"height":39},{"id":null,"href":"http://www.huffingtonpost.com/section/tv","name":null,"onclick":null,"text":"","style":null,"title":null,"className":"dropdown__column__row--link","yPosition":422,"xPosition":684,"width":194,"height":39},{"id":null,"href":"http://www.huffingtonpost.com/section/weddings","name":null,"onclick":null,"text":"","style":null,"title":null,"className":"dropdown__column__row--link","yPosition":461,"xPosition":684,"width":194,"height":39},{"id":null,"href":"http://www.huffingtonpost.com/section/weird-news","name":null,"onclick":null,"text":"","style":null,"title":null,"className":"dropdown__column__row--link","yPosition":500,"xPosition":684,"width":194,"height":39},{"id":null,"href":"http://www.huffingtonpost.com/section/women","name":null,"onclick":null,"text":"","style":null,"title":null,"className":"dropdown__column__row--link","yPosition":539,"xPosition":684,"width":194,"height":39},{"id":null,"href":"http://www.huffingtonpost.com/section/world","name":null,"onclick":null,"text":"","style":null,"title":null,"className":"dropdown__column__row--link","yPosition":578,"xPosition":684,"width":194,"height":39},{"id":null,"href":"http://www.huffingtonpost.com/news/parents-back-to-school/","name":null,"onclick":null,"text":"","style":null,"title":null,"className":"dropdown__column__row--link","yPosition":188,"xPosition":879,"width":194,"height":39},{"id":null,"href":"http://www.huffingtonpost.com/section/gps-for-the-soul","name":null,"onclick":null,"text":"","style":null,"title":null,"className":"dropdown__column__row--link","yPosition":227,"xPosition":879,"width":194,"height":39},{"id":null,"href":"http://www.huffingtonpost.com/section/hawaii","name":null,"onclick":null,"text":"","style":null,"title":null,"className":"dropdown__column__row--link","yPosition":266,"xPosition":879,"width":194,"height":39},{"id":null,"href":"http://www.huffingtonpost.com/own/","name":null,"onclick":null,"text":"","style":null,"title":null,"className":"dropdown__column__row--link","yPosition":305,"xPosition":879,"width":194,"height":39},{"id":null,"href":"http://www.huffingtonpost.com/drphil/","name":null,"onclick":null,"text":"","style":null,"title":null,"className":"dropdown__column__row--link","yPosition":344,"xPosition":879,"width":194,"height":39},{"id":null,"href":"http://www.huffingtonpost.com/news/quiet-revolution/","name":null,"onclick":null,"text":"","style":null,"title":null,"className":"dropdown__column__row--link","yPosition":383,"xPosition":879,"width":194,"height":39},{"id":null,"href":"http://www.huffingtonpost.com/news/talk-to-me/","name":null,"onclick":null,"text":"","style":null,"title":null,"className":"dropdown__column__row--link","yPosition":422,"xPosition":879,"width":194,"height":39},{"id":null,"href":"http://www.huffingtonpost.com/news/when-to-jump/","name":null,"onclick":null,"text":"","style":null,"title":null,"className":"dropdown__column__row--link","yPosition":461,"xPosition":879,"width":194,"height":39},{"id":null,"href":"http://www.huffingtonpost.com/news/better-together/","name":null,"onclick":null,"text":"","style":null,"title":null,"className":"dropdown__column__row--link","yPosition":186,"xPosition":1074,"width":193,"height":39},{"id":null,"href":"http://www.huffingtonpost.com/news/dont-stress-the-mess/","name":null,"onclick":null,"text":"","style":null,"title":null,"className":"dropdown__column__row--link","yPosition":225,"xPosition":1074,"width":193,"height":58},{"id":null,"href":"http://www.huffingtonpost.com/news/endeavor/","name":null,"onclick":null,"text":"","style":null,"title":null,"className":"dropdown__column__row--link","yPosition":283,"xPosition":1074,"width":193,"height":39},{"id":null,"href":"http://www.huffingtonpost.com/news/generation-now/","name":null,"onclick":null,"text":"","style":null,"title":null,"className":"dropdown__column__row--link","yPosition":322,"xPosition":1074,"width":193,"height":39},{"id":null,"href":"http://www.huffingtonpost.com/news/paving-the-way/","name":null,"onclick":null,"text":"","style":null,"title":null,"className":"dropdown__column__row--link","yPosition":361,"xPosition":1074,"width":193,"height":39},{"id":null,"href":"http://www.huffingtonpost.com/news/power-of-humanity/","name":null,"onclick":null,"text":"","style":null,"title":null,"className":"dropdown__column__row--link","yPosition":400,"xPosition":1074,"width":193,"height":58},{"id":null,"href":"http://www.huffingtonpost.com/news/sleep--wellness/","name":null,"onclick":null,"text":"","style":null,"title":null,"className":"dropdown__column__row--link","yPosition":458,"xPosition":1074,"width":193,"height":39},{"id":null,"href":"http://www.huffingtonpost.com/news/purpose--profit/","name":null,"onclick":null,"text":"","style":null,"title":null,"className":"dropdown__column__row--link","yPosition":497,"xPosition":1074,"width":193,"height":58},{"id":null,"href":"http://www.huffingtonpost.com/news/what-is-working-small-businesses/","name":null,"onclick":null,"text":"","style":null,"title":null,"className":"dropdown__column__row--link","yPosition":555,"xPosition":1074,"width":193,"height":58},{"id":null,"href":"/search","name":null,"onclick":null,"text":"","style":null,"title":null,"className":"nav__item nav__item--search","yPosition":80,"xPosition":1190,"width":78,"height":49},{"id":"atwAdFrame0EANA","href":"http://adinfo.aol.com/","name":null,"onclick":null,"text":"","style":"position:absolute;outline:none;right:0px;z-index:4999;margin:0 auto;width:77px;height:15px","title":null,"className":"ad_wrapper_","yPosition":254,"xPosition":970,"width":77,"height":15},{"id":null,"href":"http://www.huffingtonpost.com/news/sustainable-food/?","name":null,"onclick":null,"text":"SUSTAINABLE FOOD","style":null,"title":null,"className":"card__link","yPosition":371,"xPosition":98,"width":145,"height":19},{"id":null,"href":"http://www.huffingtonpost.com/news/philanthropy/?","name":null,"onclick":null,"text":"PHILANTHROPY","style":null,"title":null,"className":"card__link","yPosition":406,"xPosition":98,"width":114,"height":19},{"id":null,"href":"http://www.huffingtonpost.com/news/social-change/?","name":null,"onclick":null,"text":"SOCIAL CHANGE","style":null,"title":null,"className":"card__link","yPosition":441,"xPosition":98,"width":117,"height":19},{"id":null,"href":"http://www.huffingtonpost.com/news/refugee-crisis/?","name":null,"onclick":null,"text":"REFUGEE CRISIS","style":null,"title":null,"className":"card__link","yPosition":476,"xPosition":98,"width":116,"height":19},{"id":null,"href":"http://www.huffingtonpost.com/entry/mud-jeans-rent-pants_us_57d08ae8e4b06a74c9f27b8a?","name":null,"onclick":null,"text":"Why This Company Wants You To Fall In Love With People’s Old Jeans","style":null,"title":null,"className":"card__link","yPosition":720,"xPosition":98,"width":245,"height":60},{"id":null,"href":"http://www.huffingtonpost.com/entry/mud-jeans-rent-pants_us_57d08ae8e4b06a74c9f27b8a?","name":null,"onclick":null,"text":"","style":null,"title":null,"className":"card__image card__link js-card-image","yPosition":569,"xPosition":98,"width":250,"height":141},{"id":null,"href":"http://www.huffingtonpost.com/entry/transforming-the-fashion-industry_us_57ceee96e4b0a48094a58d39?","name":null,"onclick":null,"text":"We Buy A Staggering Amount Of Clothing, And Most Of It Ends Up In Landfills","style":null,"title":null,"className":"card__link","yPosition":961,"xPosition":98,"width":245,"height":60},{"id":null,"href":"http://www.huffingtonpost.com/entry/transforming-the-fashion-industry_us_57ceee96e4b0a48094a58d39?","name":null,"onclick":null,"text":"","style":null,"title":null,"className":"card__image card__link js-card-image","yPosition":811,"xPosition":98,"width":250,"height":141},{"id":null,"href":"http://www.huffingtonpost.com/entry/land-gallery-blackboard-austin-english_us_57d18bdee4b00642712c13d8?","name":null,"onclick":null,"text":"What The Art World Can Learn From A Studio For Artists With Developmental Disabilities","style":null,"title":null,"className":"card__link","yPosition":1203,"xPosition":98,"width":245,"height":60},{"id":null,"href":"http://www.huffingtonpost.com/entry/land-gallery-blackboard-austin-english_us_57d18bdee4b00642712c13d8?","name":null,"onclick":null,"text":"","style":null,"title":null,"className":"card__image card__link js-card-image","yPosition":1052,"xPosition":98,"width":250,"height":141},{"id":null,"href":"http://www.huffingtonpost.com/entry/i-wore-same-outfit-everyday_us_57c5f72ce4b0a22de092ec2b?","name":null,"onclick":null,"text":"Dressing Like A Cartoon Character Made Me Happier, Calmer And A Better Consumer","style":null,"title":null,"className":"card__link","yPosition":1445,"xPosition":98,"width":245,"height":60},{"id":null,"href":"http://www.huffingtonpost.com/entry/i-wore-same-outfit-everyday_us_57c5f72ce4b0a22de092ec2b?","name":null,"onclick":null,"text":"","style":null,"title":null,"className":"card__image card__link js-card-image","yPosition":1294,"xPosition":98,"width":250,"height":141},{"id":null,"href":"http://www.huffingtonpost.com/entry/hm-ethical_us_57d6a8a1e4b00642712e45f0?","name":null,"onclick":null,"text":"Before Buying More Clothes At H&M, Read This","style":null,"title":null,"className":"card__link","yPosition":1686,"xPosition":98,"width":245,"height":40},{"id":null,"href":"http://www.huffingtonpost.com/entry/hm-ethical_us_57d6a8a1e4b00642712e45f0?","name":null,"onclick":null,"text":"","style":null,"title":null,"className":"card__image card__link js-card-image","yPosition":1536,"xPosition":98,"width":250,"height":141},{"id":null,"href":"http://www.huffingtonpost.com/entry/these-are-the-gnarly-chemicals-in-the-cheap-clothes-we-buy_us_57d6e494e4b03d2d459b92ff?","name":null,"onclick":null,"text":"Why You Should Watch Out For These 5 Gnarly Chemicals In Your Clothing","style":null,"title":null,"className":"card__link","yPosition":1908,"xPosition":98,"width":245,"height":60},{"id":null,"href":"http://www.huffingtonpost.com/entry/these-are-the-gnarly-chemicals-in-the-cheap-clothes-we-buy_us_57d6e494e4b03d2d459b92ff?","name":null,"onclick":null,"text":"","style":null,"title":null,"className":"card__image card__link js-card-image","yPosition":1757,"xPosition":98,"width":250,"height":141},{"id":null,"href":"http://www.huffingtonpost.com/entry/essie-justice-group-gina-clayton_us_57dae854e4b0071a6e05e7fa?","name":null,"onclick":null,"text":"1 In 4 American Women Has A Family Member In Prison. Now They’re Organizing.","style":null,"title":null,"className":"card__link","yPosition":2149,"xPosition":98,"width":245,"height":60},{"id":null,"href":"http://www.huffingtonpost.com/entry/essie-justice-group-gina-clayton_us_57dae854e4b0071a6e05e7fa?","name":null,"onclick":null,"text":"","style":null,"title":null,"className":"card__image card__link js-card-image","yPosition":1999,"xPosition":98,"width":250,"height":141},{"id":null,"href":"http://www.huffingtonpost.com/entry/air-pollution-photos_us_57dbacb4e4b08cb14094e1c5?","name":null,"onclick":null,"text":"How U.S. Cities Might Look If They Polluted Like China","style":null,"title":null,"className":"card__link","yPosition":2391,"xPosition":98,"width":245,"height":40},{"id":null,"href":"http://www.huffingtonpost.com/entry/air-pollution-photos_us_57dbacb4e4b08cb14094e1c5?","name":null,"onclick":null,"text":"","style":null,"title":null,"className":"card__image card__link js-card-image","yPosition":2240,"xPosition":98,"width":250,"height":141},{"id":null,"href":"http://www.huffingtonpost.com/entry/tiny-houses-homeless-detroit_us_57d1e926e4b03d2d4599b476?","name":null,"onclick":null,"text":"This Tiny House Community Will Turn Homeless People Into Homeowners","style":null,"title":null,"className":"card__link","yPosition":2613,"xPosition":98,"width":245,"height":60},{"id":null,"href":"http://www.huffingtonpost.com/entry/tiny-houses-homeless-detroit_us_57d1e926e4b03d2d4599b476?","name":null,"onclick":null,"text":"","style":null,"title":null,"className":"card__image card__link js-card-image","yPosition":2462,"xPosition":98,"width":250,"height":141},{"id":null,"href":"http://www.huffingtonpost.com/entry/if-our-clothes-came-with-a-surgeon-generals-warning-wed-end-fast-fashion-in-an-instant_us_57cf84d0e4b0a48094a684e3?","name":null,"onclick":null,"text":"The ‘Chilling’ Moment This Father Realized Where His Kids’ Clothes Come From","style":null,"title":null,"className":"card__link","yPosition":2854,"xPosition":98,"width":245,"height":60},{"id":null,"href":"http://www.huffingtonpost.com/entry/if-our-clothes-came-with-a-surgeon-generals-warning-wed-end-fast-fashion-in-an-instant_us_57cf84d0e4b0a48094a684e3?","name":null,"onclick":null,"text":"","style":null,"title":null,"className":"card__image card__link js-card-image","yPosition":2704,"xPosition":98,"width":250,"height":141},{"id":null,"href":"http://www.huffingtonpost.com/entry/getting-rid-of-80-percent-of-closet_us_57df3b31e4b04a1497b5188e?","name":null,"onclick":null,"text":"I Just Purged 80 Percent Of My Closet. Why Do I Feel So Guilty?","style":null,"title":null,"className":"card__link","yPosition":364,"xPosition":383,"width":333,"height":56},{"id":null,"href":"http://www.huffingtonpost.com/entry/getting-rid-of-80-percent-of-closet_us_57df3b31e4b04a1497b5188e?","name":null,"onclick":null,"text":"","style":null,"title":null,"className":"card__image card__link js-card-image","yPosition":364,"xPosition":721,"width":182,"height":97},{"id":null,"href":"http://www.huffingtonpost.com/entry/these-inmates-did-a-facebook-live-from-the-county-jail_us_57e73af2e4b09f67131e4650?","name":null,"onclick":null,"text":"These Inmates Did A Facebook Live From The County Jail. Their Message Is Life-Saving.","style":null,"title":null,"className":"card__link","yPosition":521,"xPosition":383,"width":333,"height":84},{"id":null,"href":"/author/hampton-ryan-j-694","name":null,"onclick":null,"text":"","style":null,"title":null,"className":"author-card author-card--mega-phone","yPosition":636,"xPosition":383,"width":36,"height":40},{"id":null,"href":"/author/hampton-ryan-j-694","name":null,"onclick":null,"text":"Ryan Hampton","style":null,"title":null,"className":"author-card__details__link","yPosition":630,"xPosition":419,"width":105,"height":15},{"id":null,"href":"http://www.huffingtonpost.com/entry/these-inmates-did-a-facebook-live-from-the-county-jail_us_57e73af2e4b09f67131e4650?","name":null,"onclick":null,"text":"","style":null,"title":null,"className":"card__image card__link js-card-image","yPosition":521,"xPosition":721,"width":182,"height":169},{"id":null,"href":"http://www.huffingtonpost.com/entry/real-junk-food-project-supermarket-warehouse_us_57e424d5e4b0e80b1ba0e6a4?","name":null,"onclick":null,"text":"This Store Lets You Pay What You Can For Groceries That Would Otherwise Be Tossed","style":null,"title":null,"className":"card__link","yPosition":750,"xPosition":383,"width":333,"height":84},{"id":null,"href":"http://www.huffingtonpost.com/entry/real-junk-food-project-supermarket-warehouse_us_57e424d5e4b0e80b1ba0e6a4?","name":null,"onclick":null,"text":"","style":null,"title":null,"className":"card__image card__link js-card-image","yPosition":750,"xPosition":721,"width":182,"height":97},{"id":null,"href":"http://www.huffingtonpost.com/entry/kellie-jones-macarthur-curator-black-art-history_us_57e527e2e4b0e80b1ba172b8?","name":null,"onclick":null,"text":"When Kellie Jones Wanted To Study Black Art History, The Field Didn’t Exist. So She Created It Herself.","style":null,"title":null,"className":"card__link","yPosition":907,"xPosition":383,"width":333,"height":112},{"id":null,"href":"http://www.huffingtonpost.com/entry/kellie-jones-macarthur-curator-black-art-history_us_57e527e2e4b0e80b1ba172b8?","name":null,"onclick":null,"text":"","style":null,"title":null,"className":"card__image card__link js-card-image","yPosition":907,"xPosition":721,"width":182,"height":124},{"id":null,"href":"http://www.huffingtonpost.com/entry/what-your-favorite-piece-of-clothing-says-about-you_us_57e2c97ee4b0e80b1b9fc492?","name":null,"onclick":null,"text":"What Your Favorite Piece Of Clothing Says About You","style":null,"title":null,"className":"card__link","yPosition":1091,"xPosition":383,"width":333,"height":56},{"id":null,"href":"http://www.huffingtonpost.com/entry/what-your-favorite-piece-of-clothing-says-about-you_us_57e2c97ee4b0e80b1b9fc492?","name":null,"onclick":null,"text":"","style":null,"title":null,"className":"card__image card__link js-card-image","yPosition":1091,"xPosition":721,"width":182,"height":97},{"id":null,"href":"http://www.huffingtonpost.com/entry/alex-obama-omran-adopt-syrian-video_us_57e3c82ee4b08d73b82fb26c?","name":null,"onclick":null,"text":"This Video Of A Boy Asking Obama If He Can Adopt A Syrian Is Everything","style":null,"title":null,"className":"card__link","yPosition":1247,"xPosition":383,"width":333,"height":84},{"id":null,"href":"http://www.huffingtonpost.com/entry/alex-obama-omran-adopt-syrian-video_us_57e3c82ee4b08d73b82fb26c?","name":null,"onclick":null,"text":"","style":null,"title":null,"className":"card__image card__link js-card-image","yPosition":1247,"xPosition":721,"width":182,"height":97},{"id":null,"href":"http://www.huffingtonpost.com/entry/this-mother-went-a-whole-year-without-buying-clothes-for-her-family_us_57dc0c3ce4b0071a6e06d52a?","name":null,"onclick":null,"text":"This Family Went A Whole Year Without Buying New Clothes","style":null,"title":null,"className":"card__link","yPosition":1404,"xPosition":383,"width":333,"height":56},{"id":null,"href":"http://www.huffingtonpost.com/entry/this-mother-went-a-whole-year-without-buying-clothes-for-her-family_us_57dc0c3ce4b0071a6e06d52a?","name":null,"onclick":null,"text":"","style":null,"title":null,"className":"card__image card__link js-card-image","yPosition":1404,"xPosition":721,"width":182,"height":97},{"id":null,"href":"http://www.huffingtonpost.com/entry/abandoned-stadium-reuse-indianapolis_us_57dfaf6fe4b08cb140968f46?","name":null,"onclick":null,"text":"Architect Turns Abandoned Stadium Scraps Into Beautiful Bags And Bus Stops","style":null,"title":null,"className":"card__link","yPosition":1561,"xPosition":383,"width":333,"height":84},{"id":null,"href":"http://www.huffingtonpost.com/entry/abandoned-stadium-reuse-indianapolis_us_57dfaf6fe4b08cb140968f46?","name":null,"onclick":null,"text":"","style":null,"title":null,"className":"card__image card__link js-card-image","yPosition":1561,"xPosition":721,"width":182,"height":97},{"id":null,"href":"http://www.huffingtonpost.com/entry/these-african-countries-dont-want-your-used-clothing-anymore_us_57cf19bce4b06a74c9f10dd6?","name":null,"onclick":null,"text":"These African Countries Don’t Want Your Used Clothing Anymore","style":null,"title":null,"className":"card__link","yPosition":1718,"xPosition":383,"width":333,"height":56},{"id":null,"href":"http://www.huffingtonpost.com/entry/these-african-countries-dont-want-your-used-clothing-anymore_us_57cf19bce4b06a74c9f10dd6?","name":null,"onclick":null,"text":"","style":null,"title":null,"className":"card__image card__link js-card-image","yPosition":1718,"xPosition":721,"width":182,"height":97},{"id":null,"href":"http://www.huffingtonpost.com/entry/medical-marijuana-curb-opioid-use_us_57dc610ce4b0071a6e0799f8?","name":null,"onclick":null,"text":"Marijuana May Alleviate America’s Opioid Crisis, New Study Suggests","style":null,"title":null,"className":"card__link","yPosition":1874,"xPosition":383,"width":333,"height":56},{"id":null,"href":"http://www.huffingtonpost.com/entry/medical-marijuana-curb-opioid-use_us_57dc610ce4b0071a6e0799f8?","name":null,"onclick":null,"text":"","style":null,"title":null,"className":"card__image card__link js-card-image","yPosition":1874,"xPosition":721,"width":182,"height":97},{"id":null,"href":"http://www.huffingtonpost.com/entry/an-nba-player-sets-his-sights-off-the-court_us_57cd8ea8e4b0b9c5b739aa2f?","name":null,"onclick":null,"text":"An NBA Player Sets His Sights Off The Court","style":null,"title":null,"className":"card__link","yPosition":2031,"xPosition":383,"width":333,"height":56},{"id":null,"href":"/author/stevemariotti-370","name":null,"onclick":null,"text":"","style":null,"title":null,"className":"author-card author-card--mega-phone","yPosition":2118,"xPosition":383,"width":38,"height":40},{"id":null,"href":"/author/stevemariotti-370","name":null,"onclick":null,"text":"Steve Mariotti","style":null,"title":null,"className":"author-card__details__link","yPosition":2112,"xPosition":421,"width":99,"height":15},{"id":null,"href":"http://www.huffingtonpost.com/entry/an-nba-player-sets-his-sights-off-the-court_us_57cd8ea8e4b0b9c5b739aa2f?","name":null,"onclick":null,"text":"","style":null,"title":null,"className":"card__image card__link js-card-image","yPosition":2031,"xPosition":721,"width":182,"height":141},{"id":null,"href":"http://www.huffingtonpost.com/entry/food-ethics-what-experts-buy_us_57d05ebce4b06a74c9f22eab?","name":null,"onclick":null,"text":"Is There Any Food That’s Totally Ethical To Eat? Here’s What Experts Buy","style":null,"title":null,"className":"card__link","yPosition":2232,"xPosition":383,"width":333,"height":84},{"id":null,"href":"http://www.huffingtonpost.com/entry/food-ethics-what-experts-buy_us_57d05ebce4b06a74c9f22eab?","name":null,"onclick":null,"text":"","style":null,"title":null,"className":"card__image card__link js-card-image","yPosition":2232,"xPosition":721,"width":182,"height":97},{"id":null,"href":"http://www.huffingtonpost.com/entry/greek-teachers-refugees_us_57d055e9e4b06a74c9f22123?","name":null,"onclick":null,"text":"New Teachers For Refugee Kids Are A Bright Spot In Greece’s Troubled Education System","style":null,"title":null,"className":"card__link","yPosition":2389,"xPosition":383,"width":333,"height":84},{"id":null,"href":"http://www.huffingtonpost.com/entry/greek-teachers-refugees_us_57d055e9e4b06a74c9f22123?","name":null,"onclick":null,"text":"","style":null,"title":null,"className":"card__image card__link js-card-image","yPosition":2389,"xPosition":721,"width":182,"height":97},{"id":null,"href":"http://www.huffingtonpost.com/entry/second-hand-clothing-environmental-impact_us_57cf0321e4b0a48094a5c32b?","name":null,"onclick":null,"text":"Now You Can Do Your Thrift Shopping Online, And It’s About Time","style":null,"title":null,"className":"card__link","yPosition":2546,"xPosition":383,"width":333,"height":84},{"id":null,"href":"http://www.huffingtonpost.com/entry/second-hand-clothing-environmental-impact_us_57cf0321e4b0a48094a5c32b?","name":null,"onclick":null,"text":"","style":null,"title":null,"className":"card__image card__link js-card-image","yPosition":2546,"xPosition":721,"width":182,"height":97},{"id":null,"href":"http://www.huffingtonpost.com/entry/renewal-workshop-repair-resell-clothes_us_57b4c50ae4b034dc73255e41?","name":null,"onclick":null,"text":"This Company Is Basically A Hospital For Sad, Damaged Clothes","style":null,"title":null,"className":"card__link","yPosition":2702,"xPosition":383,"width":333,"height":56},{"id":null,"href":"http://www.huffingtonpost.com/entry/renewal-workshop-repair-resell-clothes_us_57b4c50ae4b034dc73255e41?","name":null,"onclick":null,"text":"","style":null,"title":null,"className":"card__image card__link js-card-image","yPosition":2702,"xPosition":721,"width":182,"height":97},{"id":null,"href":"http://www.huffingtonpost.com/entry/seoul-nuclear-energy_us_57d03babe4b03d2d4597b38e?","name":null,"onclick":null,"text":"How Japan’s Nuclear Disaster Still Haunts South Korea’s Biggest City","style":null,"title":null,"className":"card__link","yPosition":2859,"xPosition":383,"width":333,"height":56},{"id":null,"href":"http://www.huffingtonpost.com/entry/seoul-nuclear-energy_us_57d03babe4b03d2d4597b38e?","name":null,"onclick":null,"text":"","style":null,"title":null,"className":"card__image card__link js-card-image","yPosition":2859,"xPosition":721,"width":182,"height":97},{"id":null,"href":"http://www.huffingtonpost.com/entry/researchers-suggest-two-concrete-things-to-combat-hollywood-bias-against-women-and-people-of-color_us_57d1b1e1e4b06a74c9f38252?","name":null,"onclick":null,"text":"Researchers Suggest Two Concrete Ways To Combat Hollywood Bias Against Women And People Of Color","style":null,"title":null,"className":"card__link","yPosition":3016,"xPosition":383,"width":333,"height":112},{"id":null,"href":"http://www.huffingtonpost.com/entry/researchers-suggest-two-concrete-things-to-combat-hollywood-bias-against-women-and-people-of-color_us_57d1b1e1e4b06a74c9f38252?","name":null,"onclick":null,"text":"","style":null,"title":null,"className":"card__image card__link js-card-image","yPosition":3016,"xPosition":721,"width":182,"height":124},{"id":null,"href":"http://www.huffingtonpost.com/entry/to-sit-or-stand-the-answer-isnt-black-and-white_us_57d2b7a3e4b0f831f7071b06?","name":null,"onclick":null,"text":"To Sit Or Stand? The Answer Isn’t Black And White.","style":null,"title":null,"className":"card__link","yPosition":3200,"xPosition":383,"width":333,"height":56},{"id":null,"href":"/author/kathleen-144","name":null,"onclick":null,"text":"","style":null,"title":null,"className":"author-card author-card--mega-phone","yPosition":3287,"xPosition":383,"width":38,"height":40},{"id":null,"href":"/author/kathleen-144","name":null,"onclick":null,"text":"Kathleen Hale","style":null,"title":null,"className":"author-card__details__link","yPosition":3281,"xPosition":421,"width":100,"height":15},{"id":null,"href":"http://www.huffingtonpost.com/entry/to-sit-or-stand-the-answer-isnt-black-and-white_us_57d2b7a3e4b0f831f7071b06?","name":null,"onclick":null,"text":"","style":null,"title":null,"className":"card__image card__link js-card-image","yPosition":3200,"xPosition":721,"width":182,"height":141},{"id":null,"href":"http://www.huffingtonpost.com/entry/food-waste-throw-food-away_us_577e4023e4b01edea78c9c78?","name":null,"onclick":null,"text":"Here’s How Long It Took To Grow That Tomato You Just Threw Away","style":null,"title":null,"className":"card__link","yPosition":3401,"xPosition":383,"width":333,"height":56},{"id":null,"href":"http://www.huffingtonpost.com/entry/food-waste-throw-food-away_us_577e4023e4b01edea78c9c78?","name":null,"onclick":null,"text":"","style":null,"title":null,"className":"card__image card__link js-card-image","yPosition":3401,"xPosition":721,"width":182,"height":97},{"id":null,"href":"http://www.huffingtonpost.com/entry/these-facebook-responses-to-the-east-liverpool-police_us_57d6e9c7e4b0eb9a57b7b0ff?","name":null,"onclick":null,"text":"The Powerful Response To East Liverpool’s #OtherSideOfAddiction Facebook Post","style":null,"title":null,"className":"card__link","yPosition":3558,"xPosition":383,"width":333,"height":84},{"id":null,"href":"/author/hampton-ryan-j-694","name":null,"onclick":null,"text":"","style":null,"title":null,"className":"author-card author-card--mega-phone","yPosition":3673,"xPosition":383,"width":36,"height":40},{"id":null,"href":"/author/hampton-ryan-j-694","name":null,"onclick":null,"text":"Ryan Hampton","style":null,"title":null,"className":"author-card__details__link","yPosition":3667,"xPosition":419,"width":105,"height":15},{"id":null,"href":"http://www.huffingtonpost.com/entry/these-facebook-responses-to-the-east-liverpool-police_us_57d6e9c7e4b0eb9a57b7b0ff?","name":null,"onclick":null,"text":"","style":null,"title":null,"className":"card__image card__link js-card-image","yPosition":3558,"xPosition":721,"width":182,"height":169},{"id":null,"href":"http://www.huffingtonpost.com/entry/first-presidential-debate-trump-clinton_us_57e53a55e4b0e28b2b536a08?","name":null,"onclick":null,"text":"Debate Bar So Low For Donald Trump That If He Doesn’t Vomit, He’s Exceeded Expectations","style":null,"title":null,"className":"card__link","yPosition":672,"xPosition":938,"width":295,"height":60},{"id":null,"href":"http://www.huffingtonpost.com/entry/john-oliver-raisins-scandals_us_57e8c100e4b0e80b1ba2ced0?","name":null,"onclick":null,"text":"John Oliver Is Back, And He Wants You To Get ‘F**king Outraged’ Over Donald Trump’s Scandals","style":null,"title":null,"className":"card__link","yPosition":773,"xPosition":938,"width":295,"height":60},{"id":null,"href":"http://www.huffingtonpost.com/entry/matt-gaetz-jose-fernandez-tweet_us_57e878d9e4b0e80b1ba2bdc7?","name":null,"onclick":null,"text":"GOP Lawmaker Matt Gaetz Ripped For Tweet Politicizing Death Of MLB Star Jose Fernandez","style":null,"title":null,"className":"card__link","yPosition":874,"xPosition":938,"width":295,"height":60},{"id":null,"href":"http://www.huffingtonpost.com/michael-p-mcdonald/2016-early-voting-underwa_b_12184290.html?","name":null,"onclick":null,"text":"Early Voting Has Begun! Here’s What We Know So Far","style":null,"title":null,"className":"card__link","yPosition":975,"xPosition":938,"width":295,"height":40},{"id":null,"href":"/author/michael-p-mcdonald","name":null,"onclick":null,"text":"Michael P. McDonald Associate Professor, University of Florida","style":null,"title":null,"className":"card__link","yPosition":1023,"xPosition":938,"width":261,"height":30},{"id":null,"href":"http://www.huffingtonpost.com/entry/worlds-meanest-boss-tiger-mike_us_57e8b4c1e4b08d73b8321058?","name":null,"onclick":null,"text":"Edward ‘Tiger Mike’ Davis, The World’s Meanest Boss, Dead At 85","style":null,"title":null,"className":"card__link","yPosition":1102,"xPosition":938,"width":295,"height":40},{"id":null,"href":"http://privacy.aol.com","name":null,"onclick":null,"text":"Learn more","style":null,"title":null,"className":"follow-us__form__desc","yPosition":1304,"xPosition":958,"width":68,"height":15},{"id":null,"href":"http://facebook.com/HuffingtonPost","name":null,"onclick":null,"text":"8.2 M","style":null,"title":"Follow us on Facebook","className":"facebook follow-us__networks__item__link","yPosition":1421,"xPosition":958,"width":125,"height":44},{"id":null,"href":"https://twitter.com/HuffingtonPost","name":null,"onclick":null,"text":"7.69 M","style":null,"title":"Follow us on Twitter","className":"follow-us__networks__item__link twitter","yPosition":1421,"xPosition":1093,"width":125,"height":44},{"id":null,"href":"http://pinterest.com/huffingtonpost","name":null,"onclick":null,"text":"440 K","style":null,"title":"Follow us on Pinterest","className":"follow-us__networks__item__link pinterest","yPosition":1480,"xPosition":958,"width":125,"height":44},{"id":null,"href":"https://itunes.apple.com/us/artist/the-huffington-post/id908797543?mt=2","name":null,"onclick":null,"text":"Podcast","style":null,"title":"Subscribe to our Podcast","className":"follow-us__networks__item__link podcast","yPosition":1480,"xPosition":1093,"width":125,"height":44},{"id":null,"href":"#","name":null,"onclick":null,"text":"Add us on Snapchat","style":null,"title":null,"className":"follow-us__networks__item__link snapchat js-snapchat-follow","yPosition":1539,"xPosition":958,"width":260,"height":44},{"id":null,"href":"http://www.huffingtonpost.com/entry/join-protestors-in-charlotte-north-carolina-as-they-march-for-justice_us_57e5d124e4b0e80b1ba2484d?","name":null,"onclick":null,"text":"Join Protestors In North Carolina As They March For Justice","style":null,"title":null,"className":"card__link","yPosition":2124,"xPosition":938,"width":171,"height":60},{"id":null,"href":"http://www.huffingtonpost.com/entry/join-protestors-in-charlotte-north-carolina-as-they-march-for-justice_us_57e5d124e4b0e80b1ba2484d?","name":null,"onclick":null,"text":"","style":null,"title":null,"className":"card__image js-card-image card__link","yPosition":2124,"xPosition":1114,"width":124,"height":70},{"id":null,"href":"http://www.huffingtonpost.com/entry/watch-pat-mccrory-charlotte_us_57e57242e4b08d73b83122f3?","name":null,"onclick":null,"text":"N.C. Gov. Pat McCrory Addresses Unrest In Charlotte","style":null,"title":null,"className":"card__link","yPosition":2235,"xPosition":938,"width":171,"height":60},{"id":null,"href":"http://www.huffingtonpost.com/entry/watch-pat-mccrory-charlotte_us_57e57242e4b08d73b83122f3?","name":null,"onclick":null,"text":"","style":null,"title":null,"className":"card__image js-card-image card__link","yPosition":2235,"xPosition":1114,"width":124,"height":70},{"id":null,"href":"http://www.huffingtonpost.com/entry/lucky-fish-iron-deficiency_us_57e43fe7e4b08d73b8305445?","name":null,"onclick":null,"text":"This Lucky Fish Combats Iron Deficiency","style":null,"title":null,"className":"card__link","yPosition":2346,"xPosition":938,"width":171,"height":60},{"id":null,"href":"http://www.huffingtonpost.com/entry/lucky-fish-iron-deficiency_us_57e43fe7e4b08d73b8305445?","name":null,"onclick":null,"text":"","style":null,"title":null,"className":"card__image js-card-image card__link","yPosition":2346,"xPosition":1114,"width":124,"height":70},{"id":null,"href":"http://www.huffingtonpost.com/entry/cost-of-being-woman-get-lit_us_57e41ec8e4b08d73b8301b2b?","name":null,"onclick":null,"text":"This Is The Price Of Your Woman Card","style":null,"title":null,"className":"card__link","yPosition":2457,"xPosition":938,"width":171,"height":40},{"id":null,"href":"http://www.huffingtonpost.com/entry/cost-of-being-woman-get-lit_us_57e41ec8e4b08d73b8301b2b?","name":null,"onclick":null,"text":"","style":null,"title":null,"className":"card__image js-card-image card__link","yPosition":2457,"xPosition":1114,"width":124,"height":70},{"id":null,"href":"http://www.huffingtonpost.com/entry/get-lit-the-game-of-life_us_57e41caae4b0e80b1ba0d9be?","name":null,"onclick":null,"text":"The Game Of Life Is Unfair From The Start","style":null,"title":null,"className":"card__link","yPosition":2568,"xPosition":938,"width":171,"height":40},{"id":null,"href":"http://www.huffingtonpost.com/entry/get-lit-the-game-of-life_us_57e41caae4b0e80b1ba0d9be?","name":null,"onclick":null,"text":"","style":null,"title":null,"className":"card__image js-card-image card__link","yPosition":2568,"xPosition":1114,"width":124,"height":70},{"id":null,"href":"http://www.huffingtonpost.com/entry/smithsonian-museum-of-national-african-american-history-opens_us_57e401b1e4b0e28b2b52a3c1?","name":null,"onclick":null,"text":"National Museum Spotlighting African-American History, Culture Opens","style":null,"title":null,"className":"card__link","yPosition":2679,"xPosition":938,"width":171,"height":80},{"id":null,"href":"http://www.huffingtonpost.com/entry/smithsonian-museum-of-national-african-american-history-opens_us_57e401b1e4b0e28b2b52a3c1?","name":null,"onclick":null,"text":"","style":null,"title":null,"className":"card__image js-card-image card__link","yPosition":2679,"xPosition":1114,"width":124,"height":80},{"id":null,"href":"http://www.huffingtonpost.com/entry/presidential-debates-wild-moments_us_57e46163e4b0e28b2b53344f?","name":null,"onclick":null,"text":"It Will Be Hard For Clinton And Trump To Top This","style":null,"title":null,"className":"card__link","yPosition":2000,"xPosition":0,"width":0,"height":0},{"id":null,"href":"http://www.huffingtonpost.com/entry/presidential-debates-wild-moments_us_57e46163e4b0e28b2b53344f?","name":null,"onclick":null,"text":"","style":null,"title":null,"className":"card__image js-card-image card__link","yPosition":2000,"xPosition":0,"width":0,"height":0},{"id":null,"href":"http://www.huffingtonpost.com/entry/hispanic-latino-latinx-difference_us_57e40929e4b0e28b2b52b15e?","name":null,"onclick":null,"text":"The Difference Between Hispanic, Latino And Latinx","style":null,"title":null,"className":"card__link","yPosition":2000,"xPosition":0,"width":0,"height":0},{"id":null,"href":"http://www.huffingtonpost.com/entry/hispanic-latino-latinx-difference_us_57e40929e4b0e28b2b52b15e?","name":null,"onclick":null,"text":"","style":null,"title":null,"className":"card__image js-card-image card__link","yPosition":2000,"xPosition":0,"width":0,"height":0},{"id":null,"href":"http://www.huffingtonpost.com/entry/watch-donald-trump-pittsburgh_us_57e3f4fee4b0e80b1ba0a186?","name":null,"onclick":null,"text":"Donald Trump Delivers Remarks At The Shale Insight Conference In Pittsburgh","style":null,"title":null,"className":"card__link","yPosition":2000,"xPosition":0,"width":0,"height":0},{"id":null,"href":"http://www.huffingtonpost.com/entry/watch-donald-trump-pittsburgh_us_57e3f4fee4b0e80b1ba0a186?","name":null,"onclick":null,"text":"","style":null,"title":null,"className":"card__image js-card-image card__link","yPosition":2000,"xPosition":0,"width":0,"height":0},{"id":null,"href":"http://www.huffingtonpost.com/entry/watch-obama-morgan-freeman_us_57e3ef54e4b08d73b82fd79d?","name":null,"onclick":null,"text":"Obama Grants National Medal of Arts To Morgan Freeman, Mel Brooks","style":null,"title":null,"className":"card__link","yPosition":2000,"xPosition":0,"width":0,"height":0},{"id":null,"href":"http://www.huffingtonpost.com/entry/watch-obama-morgan-freeman_us_57e3ef54e4b08d73b82fd79d?","name":null,"onclick":null,"text":"","style":null,"title":null,"className":"card__image js-card-image card__link","yPosition":2000,"xPosition":0,"width":0,"height":0},{"id":null,"href":"http://www.huffingtonpost.com/entry/hillary-clinton-selfie_us_57e89b49e4b0e28b2b54b892?","name":null,"onclick":null,"text":"One Bizarre Campaign Photo Captures 2016 Perfectly","style":null,"title":null,"className":"card__link","yPosition":4004,"xPosition":98,"width":214,"height":40},{"id":null,"href":"http://www.huffingtonpost.com/entry/hillary-clinton-selfie_us_57e89b49e4b0e28b2b54b892?","name":null,"onclick":null,"text":"","style":null,"title":null,"className":"card__image js-card-image card__link","yPosition":3874,"xPosition":98,"width":214,"height":120},{"id":null,"href":"http://www.huffingtonpost.com/entry/donald-trump-strongmen_us_57e7faabe4b08d73b831df76?","name":null,"onclick":null,"text":"‘Strongmen’ Are Back. Will America Elect One?","style":null,"title":null,"className":"card__link","yPosition":4004,"xPosition":332,"width":214,"height":40},{"id":null,"href":"http://www.huffingtonpost.com/entry/donald-trump-strongmen_us_57e7faabe4b08d73b831df76?","name":null,"onclick":null,"text":"","style":null,"title":null,"className":"card__image js-card-image card__link","yPosition":3874,"xPosition":332,"width":214,"height":120},{"id":null,"href":"http://www.huffingtonpost.com/entry/houston-shooting_us_57e90eb3e4b0e28b2b54cfa9?","name":null,"onclick":null,"text":"Gunman Killed After Opening Fire Near Houston Strip Mall","style":null,"title":null,"className":"card__link","yPosition":4004,"xPosition":566,"width":214,"height":40},{"id":null,"href":"http://www.huffingtonpost.com/entry/houston-shooting_us_57e90eb3e4b0e28b2b54cfa9?","name":null,"onclick":null,"text":"","style":null,"title":null,"className":"card__image js-card-image card__link","yPosition":3874,"xPosition":566,"width":214,"height":120},{"id":null,"href":"http://www.huffingtonpost.com/entry/donald-trump-campaign-manager-debate_us_57e917a7e4b08d73b8322381?","name":null,"onclick":null,"text":"Trump Campaign Manager Bashes Reporters Ahead Of First Debate","style":null,"title":null,"className":"card__link","yPosition":4004,"xPosition":800,"width":214,"height":60},{"id":null,"href":"http://www.huffingtonpost.com/entry/donald-trump-campaign-manager-debate_us_57e917a7e4b08d73b8322381?","name":null,"onclick":null,"text":"","style":null,"title":null,"className":"card__image js-card-image card__link","yPosition":3874,"xPosition":800,"width":214,"height":120},{"id":null,"href":"http://www.huffingtonpost.com/entry/donald-trump-supports-bush-alums_us_57e8c1b6e4b0e80b1ba2cf30?","name":null,"onclick":null,"text":"Ahead Of Debate, Bush Alumni Endorse Donald Trump","style":null,"title":null,"className":"card__link","yPosition":4004,"xPosition":1034,"width":214,"height":60},{"id":null,"href":"http://www.huffingtonpost.com/entry/donald-trump-supports-bush-alums_us_57e8c1b6e4b0e80b1ba2cf30?","name":null,"onclick":null,"text":"","style":null,"title":null,"className":"card__image js-card-image card__link","yPosition":3874,"xPosition":1034,"width":214,"height":120},{"id":null,"href":"http://www.huffingtonpost.com/entry/george-w-bush-obama-picture_us_57e6b86ce4b08d73b8319e77?","name":null,"onclick":null,"text":"George W. Bush Interrupted Obama To Ask Him To Snap A Picture Of Him And It Was Amazing","style":null,"title":null,"className":"card__link","yPosition":4366,"xPosition":98,"width":273,"height":60},{"id":null,"href":"http://www.huffingtonpost.com/entry/george-w-bush-obama-picture_us_57e6b86ce4b08d73b8319e77?","name":null,"onclick":null,"text":"","style":null,"title":null,"className":"card__image js-card-image card__link","yPosition":4203,"xPosition":98,"width":273,"height":153},{"id":null,"href":"http://www.huffingtonpost.com/entry/barack-obama-anthony-bourdain-hot-dogs_us_57e89415e4b08d73b83208d5?","name":null,"onclick":null,"text":"Obama Gets Asked About Hot Dogs, Unleashes Some Fighting Words","style":null,"title":null,"className":"card__link","yPosition":4366,"xPosition":391,"width":273,"height":40},{"id":null,"href":"http://www.huffingtonpost.com/entry/barack-obama-anthony-bourdain-hot-dogs_us_57e89415e4b08d73b83208d5?","name":null,"onclick":null,"text":"","style":null,"title":null,"className":"card__image js-card-image card__link","yPosition":4203,"xPosition":391,"width":273,"height":153},{"id":null,"href":"http://www.huffingtonpost.com/entry/crohns-disease-cause_us_57e40374e4b0e28b2b52a67c?","name":null,"onclick":null,"text":"Experts May Have Finally Found The Cause Of Crohn’s Disease","style":null,"title":null,"className":"card__link","yPosition":4366,"xPosition":683,"width":273,"height":40},{"id":null,"href":"http://www.huffingtonpost.com/entry/crohns-disease-cause_us_57e40374e4b0e28b2b52a67c?","name":null,"onclick":null,"text":"","style":null,"title":null,"className":"card__image js-card-image card__link","yPosition":4203,"xPosition":683,"width":273,"height":153},{"id":null,"href":"http://www.huffingtonpost.com/entry/soups-for-health_us_57e3e915e4b0e80b1ba091ea?","name":null,"onclick":null,"text":"The 10 Soups You Need To Soothe An Upset Stomach","style":null,"title":null,"className":"card__link","yPosition":4366,"xPosition":976,"width":273,"height":40},{"id":null,"href":"http://www.huffingtonpost.com/entry/soups-for-health_us_57e3e915e4b0e80b1ba091ea?","name":null,"onclick":null,"text":"","style":null,"title":null,"className":"card__image js-card-image card__link","yPosition":4203,"xPosition":976,"width":273,"height":153},{"id":null,"href":"http://www.huffingtonpost.com/entry/arnold-palmer-iced-tea-lemonade-drink_us_57e8b4fae4b08d73b8321068?","name":null,"onclick":null,"text":"So That’s How Arnold Palmer Created Your Favorite Drink","style":null,"title":null,"className":"card__link","yPosition":4659,"xPosition":98,"width":273,"height":40},{"id":null,"href":"http://www.huffingtonpost.com/entry/arnold-palmer-iced-tea-lemonade-drink_us_57e8b4fae4b08d73b8321068?","name":null,"onclick":null,"text":"","style":null,"title":null,"className":"card__image js-card-image card__link","yPosition":4495,"xPosition":98,"width":273,"height":153},{"id":null,"href":"http://www.huffingtonpost.com/entry/rob-reiner-donald-trump-critical_us_57e8c136e4b0e80b1ba2cee4?","name":null,"onclick":null,"text":"Director Rob Reiner Unloads On Donald Trump For Pushing White Nationalism","style":null,"title":null,"className":"card__link","yPosition":4659,"xPosition":391,"width":273,"height":60},{"id":null,"href":"http://www.huffingtonpost.com/entry/rob-reiner-donald-trump-critical_us_57e8c136e4b0e80b1ba2cee4?","name":null,"onclick":null,"text":"","style":null,"title":null,"className":"card__image js-card-image card__link","yPosition":4495,"xPosition":391,"width":273,"height":153},{"id":null,"href":"http://www.huffingtonpost.com/entry/trump-campaign-not-inviting-gennifer-flowers-debate_us_57e7c8eee4b0e28b2b547760?","name":null,"onclick":null,"text":"Trump Campaign Backtracks On Inviting Gennifer Flowers To Debate","style":null,"title":null,"className":"card__link","yPosition":4659,"xPosition":683,"width":273,"height":40},{"id":null,"href":"http://www.huffingtonpost.com/entry/trump-campaign-not-inviting-gennifer-flowers-debate_us_57e7c8eee4b0e28b2b547760?","name":null,"onclick":null,"text":"","style":null,"title":null,"className":"card__image js-card-image card__link","yPosition":4495,"xPosition":683,"width":273,"height":153},{"id":null,"href":"http://www.huffingtonpost.com/entry/michelle-obama-george-w-bush-hug-photoshop-battle_us_57e78646e4b0e80b1ba27f92?","name":null,"onclick":null,"text":"Redditors Hilariously Reimagine Michelle Obama’s Hug With George W. Bush","style":null,"title":null,"className":"card__link","yPosition":4659,"xPosition":976,"width":273,"height":60},{"id":null,"href":"http://www.huffingtonpost.com/entry/michelle-obama-george-w-bush-hug-photoshop-battle_us_57e78646e4b0e80b1ba27f92?","name":null,"onclick":null,"text":"","style":null,"title":null,"className":"card__image js-card-image card__link","yPosition":4495,"xPosition":976,"width":273,"height":153},{"id":null,"href":"http://www.huffingtonpost.com","name":null,"onclick":null,"text":"","style":null,"title":null,"className":"nav-sticky__item nav-sticky__logo","yPosition":2000,"xPosition":0,"width":0,"height":0},{"id":null,"href":"http://www.huffingtonpost.com/","name":null,"onclick":null,"text":"NEWS","style":null,"title":null,"className":"nav__item__link","yPosition":2000,"xPosition":0,"width":0,"height":0},{"id":null,"href":"http://www.huffingtonpost.com/section/politics","name":null,"onclick":null,"text":"POLITICS","style":null,"title":null,"className":"nav__item__link","yPosition":2000,"xPosition":0,"width":0,"height":0},{"id":null,"href":"http://www.huffingtonpost.com/dept/entertainment","name":null,"onclick":null,"text":"ENTERTAINMENT","style":null,"title":null,"className":"nav__item__link","yPosition":2000,"xPosition":0,"width":0,"height":0},{"id":null,"href":"http://www.huffingtonpost.com/dept/wellness","name":null,"onclick":null,"text":"WELLNESS","style":null,"title":null,"className":"nav__item__link","yPosition":2000,"xPosition":0,"width":0,"height":0},{"id":null,"href":"http://www.huffingtonpost.com/dept/whats-working","name":null,"onclick":null,"text":"WHAT’S WORKING","style":null,"title":null,"className":"nav__item__link","yPosition":2000,"xPosition":0,"width":0,"height":0},{"id":null,"href":"http://www.huffingtonpost.com/dept/voices","name":null,"onclick":null,"text":"VOICES","style":null,"title":null,"className":"nav__item__link","yPosition":2000,"xPosition":0,"width":0,"height":0},{"id":null,"href":"http://www.huffingtonpost.com/section/video","name":null,"onclick":null,"text":"VIDEO","style":null,"title":null,"className":"nav__item__link","yPosition":2000,"xPosition":0,"width":0,"height":0},{"id":null,"href":"/search","name":null,"onclick":null,"text":"","style":null,"title":null,"className":"nav__item nav__item--search","yPosition":2000,"xPosition":0,"width":0,"height":0},{"id":null,"href":"https://twitter.com/HuffingtonPost","name":null,"onclick":null,"text":"","style":null,"title":null,"className":"social-list__item social-list__item--twitter","yPosition":2000,"xPosition":0,"width":0,"height":0},{"id":null,"href":"http://facebook.com/HuffingtonPost","name":null,"onclick":null,"text":"","style":null,"title":null,"className":"social-list__item social-list__item--facebook","yPosition":2000,"xPosition":0,"width":0,"height":0},{"id":null,"href":"http://pinterest.com/huffingtonpost","name":null,"onclick":null,"text":"","style":null,"title":null,"className":"social-list__item social-list__item--pinterest","yPosition":2000,"xPosition":0,"width":0,"height":0},{"id":null,"href":"http://advertising.aol.com/properties#huffington-post","name":null,"onclick":null,"text":"Advertise","style":null,"title":null,"className":"footer__list__item__link","yPosition":4844,"xPosition":571,"width":66,"height":17},{"id":null,"href":"http://www.huffingtonpost.com/syndication/","name":null,"onclick":null,"text":"RSS","style":null,"title":null,"className":"footer__list__item__link","yPosition":4844,"xPosition":654,"width":27,"height":17},{"id":null,"href":"https://careers.smartrecruiters.com/Aol/huffington-post/","name":null,"onclick":null,"text":"Careers","style":null,"title":null,"className":"footer__list__item__link","yPosition":4844,"xPosition":697,"width":54,"height":17},{"id":null,"href":"http://www.huffingtonpost.com/p/frequently-asked-question.html","name":null,"onclick":null,"text":"FAQ","style":null,"title":null,"className":"footer__list__item__link","yPosition":4844,"xPosition":768,"width":27,"height":17},{"id":null,"href":"http://www.huffingtonpost.com/terms.html","name":null,"onclick":null,"text":"User Agreement","style":null,"title":null,"className":"footer__list__item__link","yPosition":4864,"xPosition":348,"width":114,"height":17},{"id":null,"href":"http://privacy.aol.com","name":null,"onclick":null,"text":"Privacy","style":null,"title":null,"className":"footer__list__item__link","yPosition":4864,"xPosition":479,"width":51,"height":17},{"id":null,"href":"http://www.huffingtonpost.com/comment/policy/","name":null,"onclick":null,"text":"Comment Policy","style":null,"title":null,"className":"footer__list__item__link","yPosition":4864,"xPosition":546,"width":113,"height":17},{"id":null,"href":"http://www.huffingtonpost.com/p/huffington-post.html","name":null,"onclick":null,"text":"About Us","style":null,"title":null,"className":"footer__list__item__link","yPosition":4864,"xPosition":675,"width":63,"height":17},{"id":null,"href":"http://adinfo.aol.com/about-our-ads/","name":null,"onclick":null,"text":"About Our Ads","style":null,"title":null,"className":"footer__list__item__link","yPosition":4864,"xPosition":755,"width":101,"height":17},{"id":null,"href":"http://www.huffingtonpost.com/contact/","name":null,"onclick":null,"text":"Contact Us","style":null,"title":null,"className":"footer__list__item__link","yPosition":4864,"xPosition":873,"width":76,"height":17},{"id":null,"href":"http://www.huffingtonpost.com/archive/","name":null,"onclick":null,"text":"Archive","style":null,"title":null,"className":"footer__list__item__link","yPosition":4864,"xPosition":966,"width":52,"height":17}]