[{"id":null,"href":"/","name":null,"onclick":null,"text":"","style":null,"title":null,"className":"dd-logo","yPosition":140,"xPosition":581,"width":204,"height":19},{"id":null,"href":"/#","name":null,"onclick":null,"text":"Our Picks","style":null,"title":null,"className":"dd-nav-button dd-nav-wells-button dd-nav-button-our-picks","yPosition":109,"xPosition":36,"width":51,"height":42},{"id":null,"href":"/#popular","name":null,"onclick":null,"text":"Popular","style":null,"title":null,"className":"dd-nav-button dd-nav-wells-button dd-nav-button-popular","yPosition":109,"xPosition":107,"width":41,"height":42},{"id":null,"href":"/#sections","name":null,"onclick":null,"text":"Sections","style":null,"title":null,"className":"dd-nav-button dd-nav-wells-button dd-nav-button-sections","yPosition":109,"xPosition":169,"width":46,"height":42},{"id":null,"href":"#","name":null,"onclick":null,"text":"","style":null,"title":null,"className":"dd-button-open-search-page","yPosition":149,"xPosition":1300,"width":40,"height":19},{"id":null,"href":"/","name":null,"onclick":null,"text":"","style":null,"title":null,"className":"dd-logo","yPosition":2000,"xPosition":0,"width":0,"height":0},{"id":null,"href":"/#","name":null,"onclick":null,"text":"Our Picks","style":null,"title":null,"className":"dd-nav-button dd-nav-wells-button dd-nav-button-our-picks","yPosition":2000,"xPosition":0,"width":0,"height":0},{"id":null,"href":"/#popular","name":null,"onclick":null,"text":"Popular","style":null,"title":null,"className":"dd-nav-button dd-nav-wells-button dd-nav-button-popular","yPosition":2000,"xPosition":0,"width":0,"height":0},{"id":null,"href":"/#sections","name":null,"onclick":null,"text":"Sections","style":null,"title":null,"className":"dd-nav-button dd-nav-wells-button dd-nav-button-sections","yPosition":2000,"xPosition":0,"width":0,"height":0},{"id":null,"href":"#","name":null,"onclick":null,"text":"","style":null,"title":null,"className":"dd-button-open-search-page","yPosition":2000,"xPosition":0,"width":0,"height":0},{"id":null,"href":"/","name":null,"onclick":null,"text":"","style":null,"title":null,"className":"dd-logo","yPosition":2000,"xPosition":0,"width":0,"height":0},{"id":null,"href":"/#","name":null,"onclick":null,"text":"Our Picks","style":null,"title":null,"className":"dd-nav-button dd-nav-wells-button dd-nav-button-our-picks","yPosition":2000,"xPosition":0,"width":0,"height":0},{"id":null,"href":"/#popular","name":null,"onclick":null,"text":"Popular","style":null,"title":null,"className":"dd-nav-button dd-nav-wells-button dd-nav-button-popular","yPosition":2000,"xPosition":0,"width":0,"height":0},{"id":null,"href":"/#sections","name":null,"onclick":null,"text":"Sections","style":null,"title":null,"className":"dd-nav-button dd-nav-wells-button dd-nav-button-sections","yPosition":2000,"xPosition":0,"width":0,"height":0},{"id":null,"href":"#","name":null,"onclick":null,"text":"","style":null,"title":null,"className":"dd-button-open-search-page","yPosition":2000,"xPosition":0,"width":0,"height":0},{"id":null,"href":"/topics/dot-esports","name":null,"onclick":null,"text":"Dot Esports","style":null,"title":null,"className":"dd-section-title","yPosition":2000,"xPosition":0,"width":0,"height":0},{"id":null,"href":"/topics/counter-strike","name":null,"onclick":null,"text":"Counter-Strike","style":null,"title":null,"className":"dd-section-subsection","yPosition":2000,"xPosition":0,"width":0,"height":0},{"id":null,"href":"/topics/dota-2","name":null,"onclick":null,"text":"Dota 2","style":null,"title":null,"className":"dd-section-subsection","yPosition":2000,"xPosition":0,"width":0,"height":0},{"id":null,"href":"/topics/fgc","name":null,"onclick":null,"text":"FGC","style":null,"title":null,"className":"dd-section-subsection","yPosition":2000,"xPosition":0,"width":0,"height":0},{"id":null,"href":"/topics/hearthstone","name":null,"onclick":null,"text":"Hearthstone","style":null,"title":null,"className":"dd-section-subsection","yPosition":2000,"xPosition":0,"width":0,"height":0},{"id":null,"href":"/topics/league-of-legends","name":null,"onclick":null,"text":"League of Legends","style":null,"title":null,"className":"dd-section-subsection","yPosition":2000,"xPosition":0,"width":0,"height":0},{"id":null,"href":"/topics/overwatch","name":null,"onclick":null,"text":"Overwatch","style":null,"title":null,"className":"dd-section-subsection","yPosition":2000,"xPosition":0,"width":0,"height":0},{"id":null,"href":"/layer8/trump-clinton-presidential-debate-guide/","name":null,"onclick":null,"text":"","style":null,"title":null,"className":"dd-card-leadart-autocrop-wrapper","yPosition":2000,"xPosition":0,"width":0,"height":0},{"id":null,"href":"/layer8/trump-clinton-presidential-debate-guide/","name":null,"onclick":null,"text":"A cynic's guide to the first Trump–Clinton presidential debate","style":null,"title":null,"className":"dd-card-headline","yPosition":2000,"xPosition":0,"width":0,"height":0},{"id":null,"href":"/authors/amrita-khalid/","name":null,"onclick":null,"text":"Amrita Khalid","style":null,"title":null,"className":"dd-card-byline-authors","yPosition":2000,"xPosition":0,"width":0,"height":0},{"id":null,"href":"/layer8/trump-clinton-presidential-debate-guide/","name":null,"onclick":null,"text":"","style":null,"title":null,"className":"dd-card-link-all","yPosition":2000,"xPosition":0,"width":0,"height":0},{"id":null,"href":"/","name":null,"onclick":null,"text":"See all Editor's Picks →","style":null,"title":null,"className":"dd-nav-link","yPosition":2000,"xPosition":0,"width":0,"height":0},{"id":null,"href":"/unclick/this-is-powerdul-please-dont-write-something-snarky/","name":null,"onclick":null,"text":"","style":null,"title":null,"className":"dd-card-leadart-autocrop-wrapper","yPosition":2000,"xPosition":0,"width":0,"height":0},{"id":null,"href":"/unclick/this-is-powerdul-please-dont-write-something-snarky/","name":null,"onclick":null,"text":"Please don't write something snarky about this powerful new meme","style":null,"title":null,"className":"dd-card-headline","yPosition":2000,"xPosition":0,"width":0,"height":0},{"id":null,"href":"/authors/miles-klee/","name":null,"onclick":null,"text":"Miles Klee","style":null,"title":null,"className":"dd-card-byline-authors","yPosition":2000,"xPosition":0,"width":0,"height":0},{"id":null,"href":"/unclick/this-is-powerdul-please-dont-write-something-snarky/","name":null,"onclick":null,"text":"","style":null,"title":null,"className":"dd-card-link-all","yPosition":2000,"xPosition":0,"width":0,"height":0},{"id":null,"href":"/#popular","name":null,"onclick":null,"text":"See all Popular →","style":null,"title":null,"className":"dd-nav-link","yPosition":2000,"xPosition":0,"width":0,"height":0},{"id":null,"href":"/topics/debug/","name":null,"onclick":null,"text":"Debug             →","style":null,"title":null,"className":"dd-nav-link","yPosition":2000,"xPosition":0,"width":0,"height":0},{"id":null,"href":"/topics/dot-esports/","name":null,"onclick":null,"text":"Dot Esports             →","style":null,"title":null,"className":"dd-nav-link","yPosition":2000,"xPosition":0,"width":0,"height":0},{"id":null,"href":"/topics/irl/","name":null,"onclick":null,"text":"IRL             →","style":null,"title":null,"className":"dd-nav-link","yPosition":2000,"xPosition":0,"width":0,"height":0},{"id":null,"href":"/topics/layer8/","name":null,"onclick":null,"text":"→","style":null,"title":null,"className":"dd-nav-link","yPosition":2000,"xPosition":0,"width":0,"height":0},{"id":null,"href":"/topics/parsec/","name":null,"onclick":null,"text":"Parsec             →","style":null,"title":null,"className":"dd-nav-link","yPosition":2000,"xPosition":0,"width":0,"height":0},{"id":null,"href":"/topics/bazaar/","name":null,"onclick":null,"text":"The Daily Dot Bazaar             →","style":null,"title":null,"className":"dd-nav-link","yPosition":2000,"xPosition":0,"width":0,"height":0},{"id":null,"href":"/topics/unclick/","name":null,"onclick":null,"text":"Unclick             →","style":null,"title":null,"className":"dd-nav-link","yPosition":2000,"xPosition":0,"width":0,"height":0},{"id":null,"href":"/topics/upstream/","name":null,"onclick":null,"text":"Upstream             →","style":null,"title":null,"className":"dd-nav-link","yPosition":2000,"xPosition":0,"width":0,"height":0},{"id":null,"href":"http://kernelmag.dailydot.com/","name":null,"onclick":null,"text":"→","style":null,"title":null,"className":"dd-nav-link","yPosition":2000,"xPosition":0,"width":0,"height":0},{"id":null,"href":"/about/","name":null,"onclick":null,"text":"About →","style":null,"title":null,"className":"dd-nav-link","yPosition":2000,"xPosition":0,"width":0,"height":0},{"id":null,"href":"/jobs/","name":null,"onclick":null,"text":"Jobs →","style":null,"title":null,"className":"dd-nav-link","yPosition":2000,"xPosition":0,"width":0,"height":0},{"id":null,"href":"/#","name":null,"onclick":null,"text":"Feedback →","style":null,"title":null,"className":"dd-nav-link dd-satisfaction-open-button","yPosition":2000,"xPosition":0,"width":0,"height":0},{"id":null,"href":"/#","name":null,"onclick":null,"text":"→","style":null,"title":null,"className":"dd-nav-link","yPosition":2000,"xPosition":0,"width":0,"height":0},{"id":"-twitter-button","href":"https://twitter.com/intent/follow?screen_name=@dailydot","name":null,"onclick":null,"text":"","style":null,"title":null,"className":"dd-button-follow dd-button-follow-twitter","yPosition":2000,"xPosition":0,"width":0,"height":0},{"id":"-facebook-button","href":"http://facebook.com/dailydot","name":null,"onclick":null,"text":"","style":null,"title":null,"className":"dd-button-follow dd-button-follow-facebook","yPosition":2000,"xPosition":0,"width":0,"height":0},{"id":null,"href":"http://www.instagram.com/dailydot","name":null,"onclick":null,"text":"","style":null,"title":null,"className":"dd-button-follow dd-button-follow-instagram","yPosition":2000,"xPosition":0,"width":0,"height":0},{"id":"-youtube-button","href":"https://www.youtube.com/user/dailydotvideo","name":null,"onclick":null,"text":"","style":null,"title":null,"className":"dd-button-follow dd-button-follow-youtube","yPosition":2000,"xPosition":0,"width":0,"height":0},{"id":null,"href":"https://www.reddit.com/r/dailydot","name":null,"onclick":null,"text":"","style":null,"title":null,"className":"dd-button-follow dd-button-follow-reddit","yPosition":2000,"xPosition":0,"width":0,"height":0},{"id":null,"href":"http://www.pinterest.com/dailydot","name":null,"onclick":null,"text":"","style":null,"title":null,"className":"dd-button-follow dd-button-follow-pinterest","yPosition":2000,"xPosition":0,"width":0,"height":0},{"id":"-tumblr-button","href":"https://dailydot.tumblr.com/","name":null,"onclick":null,"text":"","style":null,"title":null,"className":"dd-button-follow dd-button-follow-tumblr","yPosition":2000,"xPosition":0,"width":0,"height":0},{"id":"-twitch-button","href":"https://www.twitch.tv/dailydot","name":null,"onclick":null,"text":"","style":null,"title":null,"className":"dd-button-follow dd-button-follow-twitch","yPosition":2000,"xPosition":0,"width":0,"height":0},{"id":null,"href":"/privacy-policy/","name":null,"onclick":null,"text":"Privacy Policy","style":null,"title":null,"className":"dd-show-more-link","yPosition":2000,"xPosition":0,"width":0,"height":0},{"id":null,"href":"/terms-of-use/","name":null,"onclick":null,"text":"Terms & Conditions","style":null,"title":null,"className":"dd-show-more-link","yPosition":2000,"xPosition":0,"width":0,"height":0},{"id":null,"href":"/ethics-policy/","name":null,"onclick":null,"text":"Ethics","style":null,"title":null,"className":"dd-show-more-link","yPosition":2000,"xPosition":0,"width":0,"height":0},{"id":null,"href":"/topics/dot-esports","name":null,"onclick":null,"text":"Dot Esports","style":null,"title":null,"className":"dd-section-title","yPosition":225,"xPosition":502,"width":361,"height":73},{"id":null,"href":"/topics/counter-strike","name":null,"onclick":null,"text":"Counter-Strike","style":null,"title":null,"className":"dd-section-subsection","yPosition":322,"xPosition":20,"width":1316,"height":32},{"id":null,"href":"/topics/dota-2","name":null,"onclick":null,"text":"Dota 2","style":null,"title":null,"className":"dd-section-subsection","yPosition":354,"xPosition":20,"width":1316,"height":32},{"id":null,"href":"/topics/fgc","name":null,"onclick":null,"text":"FGC","style":null,"title":null,"className":"dd-section-subsection","yPosition":386,"xPosition":20,"width":1316,"height":32},{"id":null,"href":"/topics/hearthstone","name":null,"onclick":null,"text":"Hearthstone","style":null,"title":null,"className":"dd-section-subsection","yPosition":418,"xPosition":20,"width":1316,"height":32},{"id":null,"href":"/topics/league-of-legends","name":null,"onclick":null,"text":"League of Legends","style":null,"title":null,"className":"dd-section-subsection","yPosition":450,"xPosition":20,"width":1316,"height":32},{"id":null,"href":"/topics/overwatch","name":null,"onclick":null,"text":"Overwatch","style":null,"title":null,"className":"dd-section-subsection","yPosition":482,"xPosition":20,"width":1326,"height":32},{"id":null,"href":"/esports/gamerbee-egx-brolynho/","name":null,"onclick":null,"text":"","style":null,"title":null,"className":"dd-card-leadart-autocrop-wrapper","yPosition":493,"xPosition":86,"width":342,"height":171},{"id":null,"href":"/esports/gamerbee-egx-brolynho/","name":null,"onclick":null,"text":"Gamerbee triumphs at EGX, while Brolynho clinches a Capcom Cup berth","style":null,"title":null,"className":"dd-card-headline","yPosition":684,"xPosition":106,"width":302,"height":69},{"id":null,"href":"/authors/steven-jurek/","name":null,"onclick":null,"text":"Steven Jurek","style":null,"title":null,"className":"dd-card-byline-authors","yPosition":772,"xPosition":106,"width":76,"height":15},{"id":null,"href":"/esports/gamerbee-egx-brolynho/","name":null,"onclick":null,"text":"","style":null,"title":null,"className":"dd-card-link-all","yPosition":493,"xPosition":86,"width":342,"height":396},{"id":null,"href":"/esports/philadelphia-76ers-buys-esports-teams/","name":null,"onclick":null,"text":"","style":null,"title":null,"className":"dd-card-leadart-autocrop-wrapper","yPosition":911,"xPosition":86,"width":342,"height":171},{"id":null,"href":"/esports/philadelphia-76ers-buys-esports-teams/","name":null,"onclick":null,"text":"The Philadelphia 76ers just bought a pair of esports teams","style":null,"title":null,"className":"dd-card-headline","yPosition":1102,"xPosition":106,"width":302,"height":46},{"id":null,"href":"/authors/saira-mueller/","name":null,"onclick":null,"text":"Saira Mueller","style":null,"title":null,"className":"dd-card-byline-authors","yPosition":1167,"xPosition":106,"width":79,"height":15},{"id":null,"href":"/esports/philadelphia-76ers-buys-esports-teams/","name":null,"onclick":null,"text":"","style":null,"title":null,"className":"dd-card-link-all","yPosition":911,"xPosition":86,"width":342,"height":349},{"id":null,"href":"/esports/drhippi-hearthstone-summer-championship-blizzcon/","name":null,"onclick":null,"text":"","style":null,"title":null,"className":"dd-card-leadart-autocrop-wrapper","yPosition":1282,"xPosition":86,"width":342,"height":171},{"id":null,"href":"/esports/drhippi-hearthstone-summer-championship-blizzcon/","name":null,"onclick":null,"text":"DrHippi wins Hearthstone EU Summer Championship, qualifies for BlizzCon","style":null,"title":null,"className":"dd-card-headline","yPosition":1472,"xPosition":106,"width":302,"height":69},{"id":null,"href":"/authors/sam-nordmark/","name":null,"onclick":null,"text":"Sam Nordmark","style":null,"title":null,"className":"dd-card-byline-authors","yPosition":1560,"xPosition":106,"width":90,"height":15},{"id":null,"href":"/esports/drhippi-hearthstone-summer-championship-blizzcon/","name":null,"onclick":null,"text":"","style":null,"title":null,"className":"dd-card-link-all","yPosition":1282,"xPosition":86,"width":342,"height":396},{"id":null,"href":"/esports/envyus-csgo-win-gfinity-invitational/","name":null,"onclick":null,"text":"","style":null,"title":null,"className":"dd-card-leadart-autocrop-wrapper","yPosition":1699,"xPosition":86,"width":342,"height":171},{"id":null,"href":"/esports/envyus-csgo-win-gfinity-invitational/","name":null,"onclick":null,"text":"EnVyUs CS:GO look to regain their crown after convincing victory at Gfinity Invitational","style":null,"title":null,"className":"dd-card-headline","yPosition":1890,"xPosition":106,"width":302,"height":69},{"id":null,"href":"/authors/sam-nordmark/","name":null,"onclick":null,"text":"Sam Nordmark","style":null,"title":null,"className":"dd-card-byline-authors","yPosition":1978,"xPosition":106,"width":90,"height":15},{"id":null,"href":"/esports/envyus-csgo-win-gfinity-invitational/","name":null,"onclick":null,"text":"","style":null,"title":null,"className":"dd-card-link-all","yPosition":1699,"xPosition":86,"width":342,"height":396},{"id":null,"href":"/esports/defence-yogg-hearthstone/","name":null,"onclick":null,"text":"","style":null,"title":null,"className":"dd-card-leadart-autocrop-wrapper","yPosition":2117,"xPosition":86,"width":342,"height":171},{"id":null,"href":"/esports/defence-yogg-hearthstone/","name":null,"onclick":null,"text":"In defence of Yogg-Saron, Hearthstone's most hated card","style":null,"title":null,"className":"dd-card-headline","yPosition":2308,"xPosition":106,"width":302,"height":46},{"id":null,"href":"/authors/luke-winkie/","name":null,"onclick":null,"text":"Luke Winkie","style":null,"title":null,"className":"dd-card-byline-authors","yPosition":2373,"xPosition":106,"width":72,"height":15},{"id":null,"href":"/esports/defence-yogg-hearthstone/","name":null,"onclick":null,"text":"","style":null,"title":null,"className":"dd-card-link-all","yPosition":2117,"xPosition":86,"width":342,"height":397},{"id":null,"href":"/esports/heroes-esports-lcs-league-structure/","name":null,"onclick":null,"text":"","style":null,"title":null,"className":"dd-card-leadart-autocrop-wrapper","yPosition":2536,"xPosition":86,"width":342,"height":171},{"id":null,"href":"/esports/heroes-esports-lcs-league-structure/","name":null,"onclick":null,"text":"Blizzard replace Heroes of the Storm circuit with online LCS-style league for 2017","style":null,"title":null,"className":"dd-card-headline","yPosition":2727,"xPosition":106,"width":302,"height":69},{"id":null,"href":"/authors/callum-leslie/","name":null,"onclick":null,"text":"Callum Leslie","style":null,"title":null,"className":"dd-card-byline-authors","yPosition":2815,"xPosition":106,"width":80,"height":15},{"id":null,"href":"/esports/heroes-esports-lcs-league-structure/","name":null,"onclick":null,"text":"","style":null,"title":null,"className":"dd-card-link-all","yPosition":2536,"xPosition":86,"width":342,"height":396},{"id":null,"href":"/esports/eight-german-soccer-orgs-esports-divisions/","name":null,"onclick":null,"text":"","style":null,"title":null,"className":"dd-card-leadart-autocrop-wrapper","yPosition":3014,"xPosition":86,"width":342,"height":171},{"id":null,"href":"/esports/eight-german-soccer-orgs-esports-divisions/","name":null,"onclick":null,"text":"Multiple German soccer teams reportedly getting into esports","style":null,"title":null,"className":"dd-card-headline","yPosition":3204,"xPosition":106,"width":302,"height":46},{"id":null,"href":"/authors/josh-raven/","name":null,"onclick":null,"text":"Josh Raven","style":null,"title":null,"className":"dd-card-byline-authors","yPosition":3269,"xPosition":106,"width":66,"height":15},{"id":null,"href":"/esports/eight-german-soccer-orgs-esports-divisions/","name":null,"onclick":null,"text":"","style":null,"title":null,"className":"dd-card-link-all","yPosition":3014,"xPosition":86,"width":342,"height":373},{"id":null,"href":"/esports/riot-games-esports-revenue-expands-crowdfunding/","name":null,"onclick":null,"text":"","style":null,"title":null,"className":"dd-card-leadart-autocrop-wrapper","yPosition":3408,"xPosition":86,"width":342,"height":171},{"id":null,"href":"/esports/riot-games-esports-revenue-expands-crowdfunding/","name":null,"onclick":null,"text":"Riot Games to expand in-game merchandising for teams, add Worlds skin sale revenue to prize pool","style":null,"title":null,"className":"dd-card-headline","yPosition":3599,"xPosition":106,"width":302,"height":92},{"id":null,"href":"/authors/samuel-lingle/","name":null,"onclick":null,"text":"Samuel Lingle","style":null,"title":null,"className":"dd-card-byline-authors","yPosition":3710,"xPosition":106,"width":85,"height":15},{"id":null,"href":"/esports/riot-games-esports-revenue-expands-crowdfunding/","name":null,"onclick":null,"text":"","style":null,"title":null,"className":"dd-card-link-all","yPosition":3408,"xPosition":86,"width":342,"height":467},{"id":null,"href":"/esports/tekken-7-nordic-tour-bandai-namco/","name":null,"onclick":null,"text":"","style":null,"title":null,"className":"dd-card-leadart-autocrop-wrapper","yPosition":3897,"xPosition":86,"width":342,"height":171},{"id":null,"href":"/esports/tekken-7-nordic-tour-bandai-namco/","name":null,"onclick":null,"text":"Bandai Namco announces Tekken 7 Nordic Tour series","style":null,"title":null,"className":"dd-card-headline","yPosition":4088,"xPosition":106,"width":302,"height":46},{"id":null,"href":"/authors/steven-jurek/","name":null,"onclick":null,"text":"Steven Jurek","style":null,"title":null,"className":"dd-card-byline-authors","yPosition":4153,"xPosition":106,"width":76,"height":15},{"id":null,"href":"/esports/tekken-7-nordic-tour-bandai-namco/","name":null,"onclick":null,"text":"","style":null,"title":null,"className":"dd-card-link-all","yPosition":3897,"xPosition":86,"width":342,"height":397},{"id":null,"href":"/esports/esl-vr-counter-strike/","name":null,"onclick":null,"text":"","style":null,"title":null,"className":"dd-card-leadart-autocrop-wrapper","yPosition":4316,"xPosition":86,"width":342,"height":171},{"id":null,"href":"/esports/esl-vr-counter-strike/","name":null,"onclick":null,"text":"ESL One New York to offer virtual reality Counter-Strike broadcast","style":null,"title":null,"className":"dd-card-headline","yPosition":4507,"xPosition":106,"width":302,"height":46},{"id":null,"href":"/authors/callum-leslie/","name":null,"onclick":null,"text":"Callum Leslie","style":null,"title":null,"className":"dd-card-byline-authors","yPosition":4572,"xPosition":106,"width":80,"height":15},{"id":null,"href":"/esports/esl-vr-counter-strike/","name":null,"onclick":null,"text":"","style":null,"title":null,"className":"dd-card-link-all","yPosition":4316,"xPosition":86,"width":342,"height":373},{"id":null,"href":"/esports/steeelback-vitality-2017/","name":null,"onclick":null,"text":"","style":null,"title":null,"className":"dd-card-leadart-autocrop-wrapper","yPosition":4711,"xPosition":86,"width":342,"height":171},{"id":null,"href":"/esports/steeelback-vitality-2017/","name":null,"onclick":null,"text":"Steeelback joins Team Vitality for 2017 season","style":null,"title":null,"className":"dd-card-headline","yPosition":4901,"xPosition":106,"width":302,"height":46},{"id":null,"href":"/authors/callum-leslie/","name":null,"onclick":null,"text":"Callum Leslie","style":null,"title":null,"className":"dd-card-byline-authors","yPosition":4966,"xPosition":106,"width":80,"height":15},{"id":null,"href":"/esports/steeelback-vitality-2017/","name":null,"onclick":null,"text":"","style":null,"title":null,"className":"dd-card-link-all","yPosition":4711,"xPosition":86,"width":342,"height":373},{"id":null,"href":"/esports/starcade-esports/","name":null,"onclick":null,"text":"","style":null,"title":null,"className":"dd-card-leadart-autocrop-wrapper","yPosition":5105,"xPosition":86,"width":342,"height":171},{"id":null,"href":"/esports/starcade-esports/","name":null,"onclick":null,"text":"STARCADE!: An esports origin story","style":null,"title":null,"className":"dd-card-headline","yPosition":5296,"xPosition":106,"width":302,"height":46},{"id":null,"href":"/authors/luke-winkie/","name":null,"onclick":null,"text":"Luke Winkie","style":null,"title":null,"className":"dd-card-byline-authors","yPosition":5361,"xPosition":106,"width":72,"height":15},{"id":null,"href":"/esports/starcade-esports/","name":null,"onclick":null,"text":"","style":null,"title":null,"className":"dd-card-link-all","yPosition":5105,"xPosition":86,"width":342,"height":397},{"id":null,"href":"/esports/decks-hearthstone-european-championship/","name":null,"onclick":null,"text":"","style":null,"title":null,"className":"dd-card-leadart-autocrop-wrapper","yPosition":5584,"xPosition":86,"width":342,"height":171},{"id":null,"href":"/esports/decks-hearthstone-european-championship/","name":null,"onclick":null,"text":"Druid, Shaman, and Warrior sweep the board at Hearthstone European Championship","style":null,"title":null,"className":"dd-card-headline","yPosition":5775,"xPosition":106,"width":302,"height":69},{"id":null,"href":"/authors/callum-leslie/","name":null,"onclick":null,"text":"Callum Leslie","style":null,"title":null,"className":"dd-card-byline-authors","yPosition":5863,"xPosition":106,"width":80,"height":15},{"id":null,"href":"/esports/decks-hearthstone-european-championship/","name":null,"onclick":null,"text":"","style":null,"title":null,"className":"dd-card-link-all","yPosition":5584,"xPosition":86,"width":342,"height":396},{"id":null,"href":"/esports/reunited-overwatch-team-player-owned/","name":null,"onclick":null,"text":"","style":null,"title":null,"className":"dd-card-leadart-autocrop-wrapper","yPosition":6002,"xPosition":86,"width":342,"height":171},{"id":null,"href":"/esports/reunited-overwatch-team-player-owned/","name":null,"onclick":null,"text":"REUNITED, the player-owned Overwatch org, is forging a new path for the team model","style":null,"title":null,"className":"dd-card-headline","yPosition":6193,"xPosition":106,"width":302,"height":69},{"id":null,"href":"/authors/samuel-lingle/","name":null,"onclick":null,"text":"Samuel Lingle","style":null,"title":null,"className":"dd-card-byline-authors","yPosition":6281,"xPosition":106,"width":85,"height":15},{"id":null,"href":"/esports/reunited-overwatch-team-player-owned/","name":null,"onclick":null,"text":"","style":null,"title":null,"className":"dd-card-link-all","yPosition":6002,"xPosition":86,"width":342,"height":420},{"id":null,"href":"/esports/eleague-season-two-group-stages/","name":null,"onclick":null,"text":"","style":null,"title":null,"className":"dd-card-leadart-autocrop-wrapper","yPosition":6444,"xPosition":86,"width":342,"height":171},{"id":null,"href":"/esports/eleague-season-two-group-stages/","name":null,"onclick":null,"text":"There's going to be more than one Group of Death in season two of ELEAGUE","style":null,"title":null,"className":"dd-card-headline","yPosition":6634,"xPosition":106,"width":302,"height":69},{"id":null,"href":"/authors/josh-raven/","name":null,"onclick":null,"text":"Josh Raven","style":null,"title":null,"className":"dd-card-byline-authors","yPosition":6722,"xPosition":106,"width":66,"height":15},{"id":null,"href":"/esports/eleague-season-two-group-stages/","name":null,"onclick":null,"text":"","style":null,"title":null,"className":"dd-card-link-all","yPosition":6444,"xPosition":86,"width":342,"height":372},{"id":null,"href":"/esports/batstone-hearthstone-best-decks/","name":null,"onclick":null,"text":"","style":null,"title":null,"className":"dd-card-leadart-autocrop-wrapper","yPosition":6837,"xPosition":86,"width":342,"height":171},{"id":null,"href":"/esports/batstone-hearthstone-best-decks/","name":null,"onclick":null,"text":"The coolest decks from BatStone","style":null,"title":null,"className":"dd-card-headline","yPosition":7028,"xPosition":106,"width":302,"height":23},{"id":null,"href":"/esports/batstone-hearthstone-best-decks/","name":null,"onclick":null,"text":"","style":null,"title":null,"className":"dd-card-link-all","yPosition":6837,"xPosition":86,"width":342,"height":350},{"id":null,"href":"/esports/games-16-capcom-pro-tour/","name":null,"onclick":null,"text":"","style":null,"title":null,"className":"dd-card-leadart-autocrop-wrapper","yPosition":7209,"xPosition":86,"width":342,"height":171},{"id":null,"href":"/esports/games-16-capcom-pro-tour/","name":null,"onclick":null,"text":"Capcom Pro Tour to return to the Middle East with Geek Weekend tournament","style":null,"title":null,"className":"dd-card-headline","yPosition":7400,"xPosition":106,"width":302,"height":69},{"id":null,"href":"/authors/steven-jurek/","name":null,"onclick":null,"text":"Steven Jurek","style":null,"title":null,"className":"dd-card-byline-authors","yPosition":7488,"xPosition":106,"width":76,"height":15},{"id":null,"href":"/esports/games-16-capcom-pro-tour/","name":null,"onclick":null,"text":"","style":null,"title":null,"className":"dd-card-link-all","yPosition":7209,"xPosition":86,"width":342,"height":420},{"id":null,"href":"/esports/hotmeowth-hearthstone-world-championship/","name":null,"onclick":null,"text":"","style":null,"title":null,"className":"dd-card-leadart-autocrop-wrapper","yPosition":7651,"xPosition":86,"width":342,"height":171},{"id":null,"href":"/esports/hotmeowth-hearthstone-world-championship/","name":null,"onclick":null,"text":"HOTMEOWTH books his place in the Hearthstone World Championship","style":null,"title":null,"className":"dd-card-headline","yPosition":7842,"xPosition":106,"width":302,"height":69},{"id":null,"href":"/authors/callum-leslie/","name":null,"onclick":null,"text":"Callum Leslie","style":null,"title":null,"className":"dd-card-byline-authors","yPosition":7930,"xPosition":106,"width":80,"height":15},{"id":null,"href":"/esports/hotmeowth-hearthstone-world-championship/","name":null,"onclick":null,"text":"","style":null,"title":null,"className":"dd-card-link-all","yPosition":7651,"xPosition":86,"width":342,"height":396},{"id":null,"href":"/esports/mixed-americans-japan-cup/","name":null,"onclick":null,"text":"","style":null,"title":null,"className":"dd-card-leadart-autocrop-wrapper","yPosition":8129,"xPosition":86,"width":342,"height":171},{"id":null,"href":"/esports/mixed-americans-japan-cup/","name":null,"onclick":null,"text":"Mixed performance for the Americans in Japan Cup opening day","style":null,"title":null,"className":"dd-card-headline","yPosition":8319,"xPosition":106,"width":302,"height":69},{"id":null,"href":"/authors/steven-jurek/","name":null,"onclick":null,"text":"Steven Jurek","style":null,"title":null,"className":"dd-card-byline-authors","yPosition":8407,"xPosition":106,"width":76,"height":15},{"id":null,"href":"/esports/mixed-americans-japan-cup/","name":null,"onclick":null,"text":"","style":null,"title":null,"className":"dd-card-link-all","yPosition":8129,"xPosition":86,"width":342,"height":420},{"id":null,"href":"/esports/tespa-overwatch-collegiate-series/","name":null,"onclick":null,"text":"","style":null,"title":null,"className":"dd-card-leadart-autocrop-wrapper","yPosition":8570,"xPosition":86,"width":342,"height":171},{"id":null,"href":"/esports/tespa-overwatch-collegiate-series/","name":null,"onclick":null,"text":"Tespa will host six figure collegiate Overwatch competition","style":null,"title":null,"className":"dd-card-headline","yPosition":8761,"xPosition":106,"width":302,"height":46},{"id":null,"href":"/authors/samuel-lingle/","name":null,"onclick":null,"text":"Samuel Lingle","style":null,"title":null,"className":"dd-card-byline-authors","yPosition":8826,"xPosition":106,"width":85,"height":15},{"id":null,"href":"/esports/tespa-overwatch-collegiate-series/","name":null,"onclick":null,"text":"","style":null,"title":null,"className":"dd-card-link-all","yPosition":8570,"xPosition":86,"width":342,"height":397},{"id":null,"href":"/esports/firebat-batstone-success/","name":null,"onclick":null,"text":"","style":null,"title":null,"className":"dd-card-leadart-autocrop-wrapper","yPosition":8989,"xPosition":86,"width":342,"height":171},{"id":null,"href":"/esports/firebat-batstone-success/","name":null,"onclick":null,"text":"Why Firebat's BatStone tournament was a runaway success","style":null,"title":null,"className":"dd-card-headline","yPosition":9180,"xPosition":106,"width":302,"height":69},{"id":null,"href":"/authors/callum-leslie/","name":null,"onclick":null,"text":"Callum Leslie","style":null,"title":null,"className":"dd-card-byline-authors","yPosition":9268,"xPosition":106,"width":80,"height":15},{"id":null,"href":"/esports/firebat-batstone-success/","name":null,"onclick":null,"text":"","style":null,"title":null,"className":"dd-card-link-all","yPosition":8989,"xPosition":86,"width":342,"height":396},{"id":null,"href":"/esports/ogn-overwatch-apex/","name":null,"onclick":null,"text":"","style":null,"title":null,"className":"dd-card-leadart-autocrop-wrapper","yPosition":9407,"xPosition":86,"width":342,"height":171},{"id":null,"href":"/esports/ogn-overwatch-apex/","name":null,"onclick":null,"text":"OGN will host an Overwatch pro league","style":null,"title":null,"className":"dd-card-headline","yPosition":9598,"xPosition":106,"width":302,"height":46},{"id":null,"href":"/authors/samuel-lingle/","name":null,"onclick":null,"text":"Samuel Lingle","style":null,"title":null,"className":"dd-card-byline-authors","yPosition":9663,"xPosition":106,"width":85,"height":15},{"id":null,"href":"/esports/ogn-overwatch-apex/","name":null,"onclick":null,"text":"","style":null,"title":null,"className":"dd-card-link-all","yPosition":9407,"xPosition":86,"width":342,"height":397},{"id":null,"href":"/esports/montecristo-doa-worlds/","name":null,"onclick":null,"text":"","style":null,"title":null,"className":"dd-card-leadart-autocrop-wrapper","yPosition":9826,"xPosition":86,"width":342,"height":171},{"id":null,"href":"/esports/montecristo-doa-worlds/","name":null,"onclick":null,"text":"MonteCristo, DoA won't be casting Worlds this year","style":null,"title":null,"className":"dd-card-headline","yPosition":10016,"xPosition":106,"width":302,"height":46},{"id":null,"href":"/authors/josh-raven/","name":null,"onclick":null,"text":"Josh Raven","style":null,"title":null,"className":"dd-card-byline-authors","yPosition":10081,"xPosition":106,"width":66,"height":15},{"id":null,"href":"/esports/montecristo-doa-worlds/","name":null,"onclick":null,"text":"","style":null,"title":null,"className":"dd-card-link-all","yPosition":9826,"xPosition":86,"width":342,"height":397},{"id":null,"href":"/esports/eleague-season-two-lineup/","name":null,"onclick":null,"text":"","style":null,"title":null,"className":"dd-card-leadart-autocrop-wrapper","yPosition":10244,"xPosition":86,"width":342,"height":171},{"id":null,"href":"/esports/eleague-season-two-lineup/","name":null,"onclick":null,"text":"ELEAGUE season two lineup completed after North American preliminaries","style":null,"title":null,"className":"dd-card-headline","yPosition":10435,"xPosition":106,"width":302,"height":69},{"id":null,"href":"/authors/callum-leslie/","name":null,"onclick":null,"text":"Callum Leslie","style":null,"title":null,"className":"dd-card-byline-authors","yPosition":10523,"xPosition":106,"width":80,"height":15},{"id":null,"href":"/esports/eleague-season-two-lineup/","name":null,"onclick":null,"text":"","style":null,"title":null,"className":"dd-card-link-all","yPosition":10244,"xPosition":86,"width":342,"height":396},{"id":null,"href":"/esports/alliance-new-roster/","name":null,"onclick":null,"text":"","style":null,"title":null,"className":"dd-card-leadart-autocrop-wrapper","yPosition":10722,"xPosition":86,"width":342,"height":171},{"id":null,"href":"/esports/alliance-new-roster/","name":null,"onclick":null,"text":"Alliance adds three players to Dota roster, rebrands its logo","style":null,"title":null,"className":"dd-card-headline","yPosition":10913,"xPosition":106,"width":302,"height":46},{"id":null,"href":"/authors/sam-nordmark/","name":null,"onclick":null,"text":"Sam Nordmark","style":null,"title":null,"className":"dd-card-byline-authors","yPosition":10978,"xPosition":106,"width":90,"height":15},{"id":null,"href":"/esports/alliance-new-roster/","name":null,"onclick":null,"text":"","style":null,"title":null,"className":"dd-card-link-all","yPosition":10722,"xPosition":86,"width":342,"height":397},{"id":null,"href":"/esports/evil-geniuses-ppd-arteezy-cr1t/","name":null,"onclick":null,"text":"","style":null,"title":null,"className":"dd-card-leadart-autocrop-wrapper","yPosition":11141,"xPosition":86,"width":342,"height":171},{"id":null,"href":"/esports/evil-geniuses-ppd-arteezy-cr1t/","name":null,"onclick":null,"text":"Evil Geniuses brings on Arteezy and cr1t, ppd announces retirement","style":null,"title":null,"className":"dd-card-headline","yPosition":11332,"xPosition":106,"width":302,"height":69},{"id":null,"href":"/esports/evil-geniuses-ppd-arteezy-cr1t/","name":null,"onclick":null,"text":"","style":null,"title":null,"className":"dd-card-link-all","yPosition":11141,"xPosition":86,"width":342,"height":420},{"id":null,"href":"/esports/eleague-overwatch-open-talent-groups/","name":null,"onclick":null,"text":"","style":null,"title":null,"className":"dd-card-leadart-autocrop-wrapper","yPosition":11583,"xPosition":86,"width":342,"height":171},{"id":null,"href":"/esports/eleague-overwatch-open-talent-groups/","name":null,"onclick":null,"text":"ELEAGUE reveals groups, talent for Overwatch Open finale","style":null,"title":null,"className":"dd-card-headline","yPosition":11773,"xPosition":106,"width":302,"height":46},{"id":null,"href":"/authors/samuel-lingle/","name":null,"onclick":null,"text":"Samuel Lingle","style":null,"title":null,"className":"dd-card-byline-authors","yPosition":11838,"xPosition":106,"width":85,"height":15},{"id":null,"href":"/esports/eleague-overwatch-open-talent-groups/","name":null,"onclick":null,"text":"","style":null,"title":null,"className":"dd-card-link-all","yPosition":11583,"xPosition":86,"width":342,"height":397},{"id":null,"href":"/esports/pgl-nine-deck-hearthstone/","name":null,"onclick":null,"text":"","style":null,"title":null,"className":"dd-card-leadart-autocrop-wrapper","yPosition":12001,"xPosition":86,"width":342,"height":171},{"id":null,"href":"/esports/pgl-nine-deck-hearthstone/","name":null,"onclick":null,"text":"PGL is bringing the nine-deck format back to Hearthstone","style":null,"title":null,"className":"dd-card-headline","yPosition":12192,"xPosition":106,"width":302,"height":46},{"id":null,"href":"/authors/callum-leslie/","name":null,"onclick":null,"text":"Callum Leslie","style":null,"title":null,"className":"dd-card-byline-authors","yPosition":12257,"xPosition":106,"width":80,"height":15},{"id":null,"href":"/esports/pgl-nine-deck-hearthstone/","name":null,"onclick":null,"text":"","style":null,"title":null,"className":"dd-card-link-all","yPosition":12001,"xPosition":86,"width":342,"height":397},{"id":null,"href":"/esports/steeelback-leaves-roccat/","name":null,"onclick":null,"text":"","style":null,"title":null,"className":"dd-card-leadart-autocrop-wrapper","yPosition":12420,"xPosition":86,"width":342,"height":171},{"id":null,"href":"/esports/steeelback-leaves-roccat/","name":null,"onclick":null,"text":"Steeelback leaves ROCCAT","style":null,"title":null,"className":"dd-card-headline","yPosition":12611,"xPosition":106,"width":302,"height":23},{"id":null,"href":"/authors/josh-raven/","name":null,"onclick":null,"text":"Josh Raven","style":null,"title":null,"className":"dd-card-byline-authors","yPosition":12653,"xPosition":106,"width":66,"height":15},{"id":null,"href":"/esports/steeelback-leaves-roccat/","name":null,"onclick":null,"text":"","style":null,"title":null,"className":"dd-card-link-all","yPosition":12420,"xPosition":86,"width":342,"height":350},{"id":null,"href":"/esports/fear-retires-dota-2/","name":null,"onclick":null,"text":"","style":null,"title":null,"className":"dd-card-leadart-autocrop-wrapper","yPosition":12792,"xPosition":86,"width":342,"height":171},{"id":null,"href":"/esports/fear-retires-dota-2/","name":null,"onclick":null,"text":"Fear retires from Dota 2","style":null,"title":null,"className":"dd-card-headline","yPosition":12983,"xPosition":106,"width":302,"height":23},{"id":null,"href":"/authors/sam-nordmark/","name":null,"onclick":null,"text":"Sam Nordmark","style":null,"title":null,"className":"dd-card-byline-authors","yPosition":13025,"xPosition":106,"width":90,"height":15},{"id":null,"href":"/esports/fear-retires-dota-2/","name":null,"onclick":null,"text":"","style":null,"title":null,"className":"dd-card-link-all","yPosition":12792,"xPosition":86,"width":342,"height":374},{"id":null,"href":"/esports/uc-irvine-esports-arena/","name":null,"onclick":null,"text":"","style":null,"title":null,"className":"dd-card-leadart-autocrop-wrapper","yPosition":13248,"xPosition":86,"width":342,"height":171},{"id":null,"href":"/esports/uc-irvine-esports-arena/","name":null,"onclick":null,"text":"LCS legend Bloodwater to headline UC Irvine's League of Legends team","style":null,"title":null,"className":"dd-card-headline","yPosition":13438,"xPosition":106,"width":302,"height":69},{"id":null,"href":"/authors/samuel-lingle/","name":null,"onclick":null,"text":"Samuel Lingle","style":null,"title":null,"className":"dd-card-byline-authors","yPosition":13526,"xPosition":106,"width":85,"height":15},{"id":null,"href":"/esports/uc-irvine-esports-arena/","name":null,"onclick":null,"text":"","style":null,"title":null,"className":"dd-card-link-all","yPosition":13248,"xPosition":86,"width":342,"height":396},{"id":null,"href":"/esports/reignover-clg-worlds-coach/","name":null,"onclick":null,"text":"","style":null,"title":null,"className":"dd-card-leadart-autocrop-wrapper","yPosition":13665,"xPosition":86,"width":342,"height":171},{"id":null,"href":"/esports/reignover-clg-worlds-coach/","name":null,"onclick":null,"text":"Reignover joins CLG for Worlds as a coach","style":null,"title":null,"className":"dd-card-headline","yPosition":13856,"xPosition":106,"width":302,"height":46},{"id":null,"href":"/authors/josh-raven/","name":null,"onclick":null,"text":"Josh Raven","style":null,"title":null,"className":"dd-card-byline-authors","yPosition":13921,"xPosition":106,"width":66,"height":15},{"id":null,"href":"/esports/reignover-clg-worlds-coach/","name":null,"onclick":null,"text":"","style":null,"title":null,"className":"dd-card-link-all","yPosition":13665,"xPosition":86,"width":342,"height":421},{"id":null,"href":"/esports/immortals-signs-sodipop/","name":null,"onclick":null,"text":"","style":null,"title":null,"className":"dd-card-leadart-autocrop-wrapper","yPosition":14108,"xPosition":86,"width":342,"height":171},{"id":null,"href":"/esports/immortals-signs-sodipop/","name":null,"onclick":null,"text":"Immortals jumps into Overwatch, signs Sodipop","style":null,"title":null,"className":"dd-card-headline","yPosition":14299,"xPosition":106,"width":302,"height":46},{"id":null,"href":"/authors/samuel-lingle/","name":null,"onclick":null,"text":"Samuel Lingle","style":null,"title":null,"className":"dd-card-byline-authors","yPosition":14364,"xPosition":106,"width":85,"height":15},{"id":null,"href":"/esports/immortals-signs-sodipop/","name":null,"onclick":null,"text":"","style":null,"title":null,"className":"dd-card-link-all","yPosition":14108,"xPosition":86,"width":342,"height":373},{"id":null,"href":"/esports/lol-worlds-group-stage-schedule-2016/","name":null,"onclick":null,"text":"","style":null,"title":null,"className":"dd-card-leadart-autocrop-wrapper","yPosition":14503,"xPosition":86,"width":342,"height":171},{"id":null,"href":"/esports/lol-worlds-group-stage-schedule-2016/","name":null,"onclick":null,"text":"Here's the schedule for the group stage of the League of Legends World Championship","style":null,"title":null,"className":"dd-card-headline","yPosition":14694,"xPosition":106,"width":302,"height":69},{"id":null,"href":"/authors/samuel-lingle/","name":null,"onclick":null,"text":"Samuel Lingle","style":null,"title":null,"className":"dd-card-byline-authors","yPosition":14782,"xPosition":106,"width":85,"height":15},{"id":null,"href":"/esports/lol-worlds-group-stage-schedule-2016/","name":null,"onclick":null,"text":"","style":null,"title":null,"className":"dd-card-link-all","yPosition":14503,"xPosition":86,"width":342,"height":396},{"id":null,"href":"/parsec/twitch-beat-chess-grandmaster-simon-williams/","name":null,"onclick":null,"text":"","style":null,"title":null,"className":"dd-card-leadart-autocrop-wrapper","yPosition":14921,"xPosition":86,"width":342,"height":171},{"id":null,"href":"/parsec/twitch-beat-chess-grandmaster-simon-williams/","name":null,"onclick":null,"text":"6,000 people on Twitch just beat a chess grandmaster","style":null,"title":null,"className":"dd-card-headline","yPosition":15111,"xPosition":106,"width":302,"height":46},{"id":null,"href":"/authors/dennis-scimeca/","name":null,"onclick":null,"text":"Dennis Scimeca","style":null,"title":null,"className":"dd-card-byline-authors","yPosition":15176,"xPosition":106,"width":96,"height":15},{"id":null,"href":"/parsec/twitch-beat-chess-grandmaster-simon-williams/","name":null,"onclick":null,"text":"","style":null,"title":null,"className":"dd-card-link-all","yPosition":14921,"xPosition":86,"width":342,"height":397},{"id":null,"href":"/esports/twitch-youtube-highlight-channels-legality/","name":null,"onclick":null,"text":"","style":null,"title":null,"className":"dd-card-leadart-autocrop-wrapper","yPosition":15339,"xPosition":86,"width":342,"height":171},{"id":null,"href":"/esports/twitch-youtube-highlight-channels-legality/","name":null,"onclick":null,"text":"That highlight channel you love isn't exactly legal, but it isn't going anywhere either","style":null,"title":null,"className":"dd-card-headline","yPosition":15530,"xPosition":106,"width":302,"height":69},{"id":null,"href":"/authors/luke-winkie/","name":null,"onclick":null,"text":"Luke Winkie","style":null,"title":null,"className":"dd-card-byline-authors","yPosition":15618,"xPosition":106,"width":72,"height":15},{"id":null,"href":"/esports/twitch-youtube-highlight-channels-legality/","name":null,"onclick":null,"text":"","style":null,"title":null,"className":"dd-card-link-all","yPosition":15339,"xPosition":86,"width":342,"height":444},{"id":null,"href":"/esports/north-americna-players-qualify-capcom-cup/","name":null,"onclick":null,"text":"","style":null,"title":null,"className":"dd-card-leadart-autocrop-wrapper","yPosition":15865,"xPosition":86,"width":342,"height":171},{"id":null,"href":"/esports/north-americna-players-qualify-capcom-cup/","name":null,"onclick":null,"text":"Here’s how the top North American players can qualify for the Capcom Cup","style":null,"title":null,"className":"dd-card-headline","yPosition":16056,"xPosition":106,"width":302,"height":69},{"id":null,"href":"/authors/steven-jurek/","name":null,"onclick":null,"text":"Steven Jurek","style":null,"title":null,"className":"dd-card-byline-authors","yPosition":16144,"xPosition":106,"width":76,"height":15},{"id":null,"href":"/esports/north-americna-players-qualify-capcom-cup/","name":null,"onclick":null,"text":"","style":null,"title":null,"className":"dd-card-link-all","yPosition":15865,"xPosition":86,"width":342,"height":444},{"id":null,"href":"/esports/ninjas-in-pyjamas-starseries/","name":null,"onclick":null,"text":"","style":null,"title":null,"className":"dd-card-leadart-autocrop-wrapper","yPosition":16331,"xPosition":86,"width":342,"height":171},{"id":null,"href":"/esports/ninjas-in-pyjamas-starseries/","name":null,"onclick":null,"text":"Ninjas in Pyjamas triumph at StarSeries Season 2 LAN finals","style":null,"title":null,"className":"dd-card-headline","yPosition":16522,"xPosition":106,"width":302,"height":46},{"id":null,"href":"/authors/sam-nordmark/","name":null,"onclick":null,"text":"Sam Nordmark","style":null,"title":null,"className":"dd-card-byline-authors","yPosition":16587,"xPosition":106,"width":90,"height":15},{"id":null,"href":"/esports/ninjas-in-pyjamas-starseries/","name":null,"onclick":null,"text":"","style":null,"title":null,"className":"dd-card-link-all","yPosition":16331,"xPosition":86,"width":342,"height":373},{"id":null,"href":"/esports/fer-returns-sk-gaming/","name":null,"onclick":null,"text":"","style":null,"title":null,"className":"dd-card-leadart-autocrop-wrapper","yPosition":16726,"xPosition":86,"width":342,"height":171},{"id":null,"href":"/esports/fer-returns-sk-gaming/","name":null,"onclick":null,"text":"Fer returns to SK Gaming lineup after recovering from surgery","style":null,"title":null,"className":"dd-card-headline","yPosition":16916,"xPosition":106,"width":302,"height":46},{"id":null,"href":"/authors/sam-nordmark/","name":null,"onclick":null,"text":"Sam Nordmark","style":null,"title":null,"className":"dd-card-byline-authors","yPosition":16981,"xPosition":106,"width":90,"height":15},{"id":null,"href":"/esports/fer-returns-sk-gaming/","name":null,"onclick":null,"text":"","style":null,"title":null,"className":"dd-card-link-all","yPosition":16726,"xPosition":86,"width":342,"height":397},{"id":null,"href":"/esports/cloud9-nip-g2-dignitas-starseries/","name":null,"onclick":null,"text":"","style":null,"title":null,"className":"dd-card-leadart-autocrop-wrapper","yPosition":17144,"xPosition":86,"width":342,"height":171},{"id":null,"href":"/esports/cloud9-nip-g2-dignitas-starseries/","name":null,"onclick":null,"text":"Cloud9, Ninjas in Pyjamas, G2 Esports and Team Dignitas reach StarSeries semifinals","style":null,"title":null,"className":"dd-card-headline","yPosition":17335,"xPosition":106,"width":302,"height":69},{"id":null,"href":"/authors/sam-nordmark/","name":null,"onclick":null,"text":"Sam Nordmark","style":null,"title":null,"className":"dd-card-byline-authors","yPosition":17423,"xPosition":106,"width":90,"height":15},{"id":null,"href":"/esports/cloud9-nip-g2-dignitas-starseries/","name":null,"onclick":null,"text":"","style":null,"title":null,"className":"dd-card-link-all","yPosition":17144,"xPosition":86,"width":342,"height":420},{"id":null,"href":"/esports/groups-league-world-championship/","name":null,"onclick":null,"text":"","style":null,"title":null,"className":"dd-card-leadart-autocrop-wrapper","yPosition":17586,"xPosition":86,"width":342,"height":171},{"id":null,"href":"/esports/groups-league-world-championship/","name":null,"onclick":null,"text":"Groups drawn for League of Legends World Championship","style":null,"title":null,"className":"dd-card-headline","yPosition":17777,"xPosition":106,"width":302,"height":46},{"id":null,"href":"/authors/callum-leslie/","name":null,"onclick":null,"text":"Callum Leslie","style":null,"title":null,"className":"dd-card-byline-authors","yPosition":17842,"xPosition":106,"width":80,"height":15},{"id":null,"href":"/esports/groups-league-world-championship/","name":null,"onclick":null,"text":"","style":null,"title":null,"className":"dd-card-link-all","yPosition":17586,"xPosition":86,"width":342,"height":373},{"id":null,"href":"/esports/overwatch-world-cup-qualifying-europe/","name":null,"onclick":null,"text":"","style":null,"title":null,"className":"dd-card-leadart-autocrop-wrapper","yPosition":17981,"xPosition":86,"width":342,"height":171},{"id":null,"href":"/esports/overwatch-world-cup-qualifying-europe/","name":null,"onclick":null,"text":"Overwatch World Cup qualifying is live in Europe—here's what you need to know","style":null,"title":null,"className":"dd-card-headline","yPosition":18172,"xPosition":106,"width":302,"height":69},{"id":null,"href":"/authors/samuel-lingle/","name":null,"onclick":null,"text":"Samuel Lingle","style":null,"title":null,"className":"dd-card-byline-authors","yPosition":18260,"xPosition":106,"width":85,"height":15},{"id":null,"href":"/esports/overwatch-world-cup-qualifying-europe/","name":null,"onclick":null,"text":"","style":null,"title":null,"className":"dd-card-link-all","yPosition":17981,"xPosition":86,"width":342,"height":396},{"id":null,"href":"/esports/starseries-csgo-surprise-knockouts/","name":null,"onclick":null,"text":"","style":null,"title":null,"className":"dd-card-leadart-autocrop-wrapper","yPosition":18459,"xPosition":86,"width":342,"height":171},{"id":null,"href":"/esports/starseries-csgo-surprise-knockouts/","name":null,"onclick":null,"text":"More surprise knockouts in CS:GO, this time at Starseries","style":null,"title":null,"className":"dd-card-headline","yPosition":18649,"xPosition":106,"width":302,"height":46},{"id":null,"href":"/authors/josh-raven/","name":null,"onclick":null,"text":"Josh Raven","style":null,"title":null,"className":"dd-card-byline-authors","yPosition":18714,"xPosition":106,"width":66,"height":15},{"id":null,"href":"/esports/starseries-csgo-surprise-knockouts/","name":null,"onclick":null,"text":"","style":null,"title":null,"className":"dd-card-link-all","yPosition":18459,"xPosition":86,"width":342,"height":373},{"id":null,"href":"/esports/one-night-karazhan-cards/","name":null,"onclick":null,"text":"","style":null,"title":null,"className":"dd-card-leadart-autocrop-wrapper","yPosition":18853,"xPosition":86,"width":342,"height":171},{"id":null,"href":"/esports/one-night-karazhan-cards/","name":null,"onclick":null,"text":"The One Night in Karazhan cards that have surprised us the most","style":null,"title":null,"className":"dd-card-headline","yPosition":19044,"xPosition":106,"width":302,"height":46},{"id":null,"href":"/authors/luke-winkie/","name":null,"onclick":null,"text":"Luke Winkie","style":null,"title":null,"className":"dd-card-byline-authors","yPosition":19109,"xPosition":106,"width":72,"height":15},{"id":null,"href":"/esports/one-night-karazhan-cards/","name":null,"onclick":null,"text":"","style":null,"title":null,"className":"dd-card-link-all","yPosition":18853,"xPosition":86,"width":342,"height":373},{"id":null,"href":"/esports/alternate-godsent-dignitas-eleague/","name":null,"onclick":null,"text":"","style":null,"title":null,"className":"dd-card-leadart-autocrop-wrapper","yPosition":19248,"xPosition":86,"width":342,"height":171},{"id":null,"href":"/esports/alternate-godsent-dignitas-eleague/","name":null,"onclick":null,"text":"Alternate shock GODSENT in ELEAGUE qualifiers","style":null,"title":null,"className":"dd-card-headline","yPosition":19439,"xPosition":106,"width":302,"height":46},{"id":null,"href":"/authors/callum-leslie/","name":null,"onclick":null,"text":"Callum Leslie","style":null,"title":null,"className":"dd-card-byline-authors","yPosition":19504,"xPosition":106,"width":80,"height":15},{"id":null,"href":"/esports/alternate-godsent-dignitas-eleague/","name":null,"onclick":null,"text":"","style":null,"title":null,"className":"dd-card-link-all","yPosition":19248,"xPosition":86,"width":342,"height":373},{"id":null,"href":"/esports/hearthstone-arena-card-bans/","name":null,"onclick":null,"text":"","style":null,"title":null,"className":"dd-card-leadart-autocrop-wrapper","yPosition":19643,"xPosition":86,"width":342,"height":171},{"id":null,"href":"/esports/hearthstone-arena-card-bans/","name":null,"onclick":null,"text":"Hearthstone removes 45 cards from Arena as clamour for competitive card bans grows","style":null,"title":null,"className":"dd-card-headline","yPosition":19834,"xPosition":106,"width":302,"height":69},{"id":null,"href":"/authors/callum-leslie/","name":null,"onclick":null,"text":"Callum Leslie","style":null,"title":null,"className":"dd-card-byline-authors","yPosition":19922,"xPosition":106,"width":80,"height":15},{"id":null,"href":"/esports/hearthstone-arena-card-bans/","name":null,"onclick":null,"text":"","style":null,"title":null,"className":"dd-card-link-all","yPosition":19643,"xPosition":86,"width":342,"height":396},{"id":null,"href":"/esports/immortals-ceo-disappointing-year/","name":null,"onclick":null,"text":"","style":null,"title":null,"className":"dd-card-leadart-autocrop-wrapper","yPosition":20061,"xPosition":86,"width":342,"height":171},{"id":null,"href":"/esports/immortals-ceo-disappointing-year/","name":null,"onclick":null,"text":"Immortals will let players seek other offers after disappointing season","style":null,"title":null,"className":"dd-card-headline","yPosition":20251,"xPosition":106,"width":302,"height":69},{"id":null,"href":"/authors/samuel-lingle/","name":null,"onclick":null,"text":"Samuel Lingle","style":null,"title":null,"className":"dd-card-byline-authors","yPosition":20339,"xPosition":106,"width":85,"height":15},{"id":null,"href":"/esports/immortals-ceo-disappointing-year/","name":null,"onclick":null,"text":"","style":null,"title":null,"className":"dd-card-link-all","yPosition":20061,"xPosition":86,"width":342,"height":420},{"id":null,"href":"/esports/overwatch-play-of-the-game-weirdest/","name":null,"onclick":null,"text":"","style":null,"title":null,"className":"dd-card-leadart-autocrop-wrapper","yPosition":20502,"xPosition":86,"width":342,"height":171},{"id":null,"href":"/esports/overwatch-play-of-the-game-weirdest/","name":null,"onclick":null,"text":"The most hilariously weird Plays of the Game in Overwatch","style":null,"title":null,"className":"dd-card-headline","yPosition":20693,"xPosition":106,"width":302,"height":46},{"id":null,"href":"/authors/luke-winkie/","name":null,"onclick":null,"text":"Luke Winkie","style":null,"title":null,"className":"dd-card-byline-authors","yPosition":20758,"xPosition":106,"width":72,"height":15},{"id":null,"href":"/esports/overwatch-play-of-the-game-weirdest/","name":null,"onclick":null,"text":"","style":null,"title":null,"className":"dd-card-link-all","yPosition":20502,"xPosition":86,"width":342,"height":349},{"id":null,"href":"/esports/amaz-confirms-archon/","name":null,"onclick":null,"text":"","style":null,"title":null,"className":"dd-card-leadart-autocrop-wrapper","yPosition":20933,"xPosition":86,"width":342,"height":171},{"id":null,"href":"/esports/amaz-confirms-archon/","name":null,"onclick":null,"text":"Amaz confirms Archon shut down, sheds light on financial issues","style":null,"title":null,"className":"dd-card-headline","yPosition":21124,"xPosition":106,"width":302,"height":46},{"id":null,"href":"/authors/callum-leslie/","name":null,"onclick":null,"text":"Callum Leslie","style":null,"title":null,"className":"dd-card-byline-authors","yPosition":21189,"xPosition":106,"width":80,"height":15},{"id":null,"href":"/esports/amaz-confirms-archon/","name":null,"onclick":null,"text":"","style":null,"title":null,"className":"dd-card-link-all","yPosition":20933,"xPosition":86,"width":342,"height":373},{"id":null,"href":"/esports/is-hearthstone-dying/","name":null,"onclick":null,"text":"","style":null,"title":null,"className":"dd-card-leadart-autocrop-wrapper","yPosition":21328,"xPosition":86,"width":342,"height":171},{"id":null,"href":"/esports/is-hearthstone-dying/","name":null,"onclick":null,"text":"Competitive Hearthstone isn't dying, but it might be changing forever","style":null,"title":null,"className":"dd-card-headline","yPosition":21519,"xPosition":106,"width":302,"height":69},{"id":null,"href":"/authors/callum-leslie/","name":null,"onclick":null,"text":"Callum Leslie","style":null,"title":null,"className":"dd-card-byline-authors","yPosition":21607,"xPosition":106,"width":80,"height":15},{"id":null,"href":"/esports/is-hearthstone-dying/","name":null,"onclick":null,"text":"","style":null,"title":null,"className":"dd-card-link-all","yPosition":21328,"xPosition":86,"width":342,"height":420},{"id":null,"href":"/esports/eleague-csgo-season-two-eu-closed-quals/","name":null,"onclick":null,"text":"","style":null,"title":null,"className":"dd-card-leadart-autocrop-wrapper","yPosition":21770,"xPosition":86,"width":342,"height":171},{"id":null,"href":"/esports/eleague-csgo-season-two-eu-closed-quals/","name":null,"onclick":null,"text":"ELEAGUE's CS:GO qualifiers for EU are almost over","style":null,"title":null,"className":"dd-card-headline","yPosition":21960,"xPosition":106,"width":302,"height":46},{"id":null,"href":"/authors/josh-raven/","name":null,"onclick":null,"text":"Josh Raven","style":null,"title":null,"className":"dd-card-byline-authors","yPosition":22025,"xPosition":106,"width":66,"height":15},{"id":null,"href":"/esports/eleague-csgo-season-two-eu-closed-quals/","name":null,"onclick":null,"text":"","style":null,"title":null,"className":"dd-card-link-all","yPosition":21770,"xPosition":86,"width":342,"height":397},{"id":null,"href":"/esports/csgo-na-esports-pea/","name":null,"onclick":null,"text":"","style":null,"title":null,"className":"dd-card-leadart-autocrop-wrapper","yPosition":22188,"xPosition":86,"width":342,"height":171},{"id":null,"href":"/esports/csgo-na-esports-pea/","name":null,"onclick":null,"text":"Seven major NA esports orgs band together to create owner-operated CS:GO league","style":null,"title":null,"className":"dd-card-headline","yPosition":22379,"xPosition":106,"width":302,"height":69},{"id":null,"href":"/esports/csgo-na-esports-pea/","name":null,"onclick":null,"text":"","style":null,"title":null,"className":"dd-card-link-all","yPosition":22188,"xPosition":86,"width":342,"height":396},{"id":null,"href":"/esports/dreamhack-austin-usa/","name":null,"onclick":null,"text":"","style":null,"title":null,"className":"dd-card-leadart-autocrop-wrapper","yPosition":22606,"xPosition":86,"width":342,"height":171},{"id":null,"href":"/esports/dreamhack-austin-usa/","name":null,"onclick":null,"text":"DreamHack Austin is back in 2017, two new US locations to be announced","style":null,"title":null,"className":"dd-card-headline","yPosition":22797,"xPosition":106,"width":302,"height":69},{"id":null,"href":"/authors/saira-mueller/","name":null,"onclick":null,"text":"Saira Mueller","style":null,"title":null,"className":"dd-card-byline-authors","yPosition":22885,"xPosition":106,"width":79,"height":15},{"id":null,"href":"/esports/dreamhack-austin-usa/","name":null,"onclick":null,"text":"","style":null,"title":null,"className":"dd-card-link-all","yPosition":22606,"xPosition":86,"width":342,"height":396},{"id":null,"href":"/esports/navi-suspends-operation-hearthstone-team/","name":null,"onclick":null,"text":"","style":null,"title":null,"className":"dd-card-leadart-autocrop-wrapper","yPosition":23024,"xPosition":86,"width":342,"height":171},{"id":null,"href":"/esports/navi-suspends-operation-hearthstone-team/","name":null,"onclick":null,"text":"Na`Vi shuts down its Hearthstone department","style":null,"title":null,"className":"dd-card-headline","yPosition":23215,"xPosition":106,"width":302,"height":46},{"id":null,"href":"/authors/saira-mueller/","name":null,"onclick":null,"text":"Saira Mueller","style":null,"title":null,"className":"dd-card-byline-authors","yPosition":23280,"xPosition":106,"width":79,"height":15},{"id":null,"href":"/esports/navi-suspends-operation-hearthstone-team/","name":null,"onclick":null,"text":"","style":null,"title":null,"className":"dd-card-link-all","yPosition":23024,"xPosition":86,"width":342,"height":397},{"id":null,"href":"/esports/lcs-summer-split-biggest-surprises/","name":null,"onclick":null,"text":"","style":null,"title":null,"className":"dd-card-leadart-autocrop-wrapper","yPosition":23503,"xPosition":86,"width":342,"height":171},{"id":null,"href":"/esports/lcs-summer-split-biggest-surprises/","name":null,"onclick":null,"text":"The biggest surprises of the Summer Split","style":null,"title":null,"className":"dd-card-headline","yPosition":23693,"xPosition":106,"width":302,"height":46},{"id":null,"href":"/authors/josh-raven/","name":null,"onclick":null,"text":"Josh Raven","style":null,"title":null,"className":"dd-card-byline-authors","yPosition":23758,"xPosition":106,"width":66,"height":15},{"id":null,"href":"/esports/lcs-summer-split-biggest-surprises/","name":null,"onclick":null,"text":"","style":null,"title":null,"className":"dd-card-link-all","yPosition":23503,"xPosition":86,"width":342,"height":349},{"id":null,"href":"/esports/evo-japan-1-million-investment/","name":null,"onclick":null,"text":"","style":null,"title":null,"className":"dd-card-leadart-autocrop-wrapper","yPosition":23873,"xPosition":86,"width":342,"height":171},{"id":null,"href":"/esports/evo-japan-1-million-investment/","name":null,"onclick":null,"text":"Evo Japan gets $1 million investment","style":null,"title":null,"className":"dd-card-headline","yPosition":24064,"xPosition":106,"width":302,"height":46},{"id":null,"href":"/authors/steven-jurek/","name":null,"onclick":null,"text":"Steven Jurek","style":null,"title":null,"className":"dd-card-byline-authors","yPosition":24129,"xPosition":106,"width":76,"height":15},{"id":null,"href":"/esports/evo-japan-1-million-investment/","name":null,"onclick":null,"text":"","style":null,"title":null,"className":"dd-card-link-all","yPosition":23873,"xPosition":86,"width":342,"height":397},{"id":null,"href":"/esports/amaz-signs-nrg-esports-archon/","name":null,"onclick":null,"text":"","style":null,"title":null,"className":"dd-card-leadart-autocrop-wrapper","yPosition":24292,"xPosition":86,"width":342,"height":171},{"id":null,"href":"/esports/amaz-signs-nrg-esports-archon/","name":null,"onclick":null,"text":"Amaz signs with NRG, future of Archon unclear","style":null,"title":null,"className":"dd-card-headline","yPosition":24483,"xPosition":106,"width":302,"height":46},{"id":null,"href":"/authors/samuel-lingle/","name":null,"onclick":null,"text":"Samuel Lingle","style":null,"title":null,"className":"dd-card-byline-authors","yPosition":24548,"xPosition":106,"width":85,"height":15},{"id":null,"href":"/esports/amaz-signs-nrg-esports-archon/","name":null,"onclick":null,"text":"","style":null,"title":null,"className":"dd-card-link-all","yPosition":24292,"xPosition":86,"width":342,"height":421},{"id":null,"href":"/esports/riot-games-league-of-legends-esports-mistakes/","name":null,"onclick":null,"text":"","style":null,"title":null,"className":"dd-card-leadart-autocrop-wrapper","yPosition":24735,"xPosition":86,"width":342,"height":171},{"id":null,"href":"/esports/riot-games-league-of-legends-esports-mistakes/","name":null,"onclick":null,"text":"Riot's 5 biggest mistakes","style":null,"title":null,"className":"dd-card-headline","yPosition":24926,"xPosition":106,"width":302,"height":23},{"id":null,"href":"/authors/sam-nordmark/","name":null,"onclick":null,"text":"Sam Nordmark","style":null,"title":null,"className":"dd-card-byline-authors","yPosition":24968,"xPosition":106,"width":90,"height":15},{"id":null,"href":"/esports/riot-games-league-of-legends-esports-mistakes/","name":null,"onclick":null,"text":"","style":null,"title":null,"className":"dd-card-link-all","yPosition":24735,"xPosition":86,"width":342,"height":374},{"id":null,"href":"/esports/hearthstone-expansions-adventures-power-rankings/","name":null,"onclick":null,"text":"","style":null,"title":null,"className":"dd-card-leadart-autocrop-wrapper","yPosition":25131,"xPosition":86,"width":342,"height":171},{"id":null,"href":"/esports/hearthstone-expansions-adventures-power-rankings/","name":null,"onclick":null,"text":"Every Hearthstone expansion, ranked","style":null,"title":null,"className":"dd-card-headline","yPosition":25321,"xPosition":106,"width":302,"height":46},{"id":null,"href":"/authors/luke-winkie/","name":null,"onclick":null,"text":"Luke Winkie","style":null,"title":null,"className":"dd-card-byline-authors","yPosition":25386,"xPosition":106,"width":72,"height":15},{"id":null,"href":"/esports/hearthstone-expansions-adventures-power-rankings/","name":null,"onclick":null,"text":"","style":null,"title":null,"className":"dd-card-link-all","yPosition":25131,"xPosition":86,"width":342,"height":397},{"id":null,"href":"/esports/fnatic-dota-2-sign-three-tnc-gaming-players/","name":null,"onclick":null,"text":"","style":null,"title":null,"className":"dd-card-leadart-autocrop-wrapper","yPosition":25549,"xPosition":86,"width":342,"height":171},{"id":null,"href":"/esports/fnatic-dota-2-sign-three-tnc-gaming-players/","name":null,"onclick":null,"text":"Fnatic recruits majority of TNC Gaming’s TI6 roster","style":null,"title":null,"className":"dd-card-headline","yPosition":25740,"xPosition":106,"width":302,"height":46},{"id":null,"href":"/authors/sam-nordmark/","name":null,"onclick":null,"text":"Sam Nordmark","style":null,"title":null,"className":"dd-card-byline-authors","yPosition":25805,"xPosition":106,"width":90,"height":15},{"id":null,"href":"/esports/fnatic-dota-2-sign-three-tnc-gaming-players/","name":null,"onclick":null,"text":"","style":null,"title":null,"className":"dd-card-link-all","yPosition":25549,"xPosition":86,"width":342,"height":397},{"id":null,"href":"/","name":null,"onclick":null,"text":"","style":null,"title":null,"className":"dd-logo","yPosition":2000,"xPosition":0,"width":0,"height":0},{"id":null,"href":"#","name":null,"onclick":null,"text":"","style":null,"title":null,"className":"dd-button-close-search-takeover","yPosition":2000,"xPosition":0,"width":0,"height":0},{"id":null,"href":"/search/?q=Donald%20Trump","name":null,"onclick":null,"text":"Donald Trump","style":null,"title":null,"className":"dd-search-text-recommendations","yPosition":2000,"xPosition":0,"width":0,"height":0},{"id":null,"href":"/search/?q=Apple%20vs.%20FBI","name":null,"onclick":null,"text":"Apple vs. FBI","style":null,"title":null,"className":"dd-search-text-recommendations","yPosition":2000,"xPosition":0,"width":0,"height":0},{"id":null,"href":"/search/?q=%23OscarsSoWhite","name":null,"onclick":null,"text":"#OscarsSoWhite","style":null,"title":null,"className":"dd-search-text-recommendations","yPosition":2000,"xPosition":0,"width":0,"height":0},{"id":null,"href":"/search/?q=2016%20Election","name":null,"onclick":null,"text":"2016 Election","style":null,"title":null,"className":"dd-search-text-recommendations","yPosition":2000,"xPosition":0,"width":0,"height":0},{"id":null,"href":"/search/?q=30%20Days%20of%20Star%20Wars","name":null,"onclick":null,"text":"30 Days of Star Wars","style":null,"title":null,"className":"dd-search-text-recommendations","yPosition":2000,"xPosition":0,"width":0,"height":0}]